Workbook

Sheet Master Plan
A1: Master Order | B1: Phase / Timing | C1: Lane | D1: Resource / Activity | E1: Provider | F1: Priority | G1: Effort (h) | H1: What to Do | I1: Proof / Deliverable | J1: Source Sheet | K1: Detail | L1: External Link | M1: Status | N1: Notes | O1: Target Start | P1: Target Finish | R1: =HYPERLINK("#'Competency Matrix'!A1","Open Competency Matrix") -> Open Competency Matrix
A2: 1 | B2: Week 1 — Agent fundamentals | C2: CORE — Agent Engineering | D2: Build Agents with Agent Development Kit (ADK) | E2: Google Skills / GEAR | F2: VERY HIGH | G2: 0.5 | H2: Understand ADK's code-first agent model and core abstractions. | I2: Sketch an agent loop and map ADK Agent/Tool/Session concepts onto it. | J2: Roadmap | K2: Go to detail | L2: Open resource | M2: Done | N2: 1-page architecture note: 'What ADK abstracts vs what it does not'. | O2: 46296 | P2: 46302 | R2: =HYPERLINK("#'Revision'!A1","Revision / Refresh Guide") -> Revision / Refresh Guide
A3: 2 | B3: Week 1 — First ADK agent | C3: CORE — Agent Engineering | D3: Build Your First Agent with ADK | E3: Google Skills / GEAR | F3: VERY HIGH | G3: 1 | H3: Create, configure, and run ADK agents in Python/YAML. | I3: Build the lab, close instructions, then recreate from memory with one custom behavior. | J3: Roadmap | K3: Go to detail | L3: Open resource | M3: Not Started | N3: Repo: first-adk-agent + README + run instructions. | O3: 46296 | P3: 46302
A4: 3 | B4: Week 1 — ADK foundations | C4: CORE — Agent Engineering | D4: Building AI Agents with ADK: The Foundation | E4: Google Codelabs | F4: VERY HIGH | G4: 1 | H4: Set up ADK and build a foundational conversational agent. | I4: Complete codelab, then add structured output and one failure test. | J4: Roadmap | K4: Go to detail | L4: Open resource | M4: Not Started | N4: Commit tagged foundation-v1 with tests. | O4: 46296 | P4: 46302
A5: 4 | B5: Week 1 — ADK mental model | C5: CORE — Agent Engineering | D5: Introducing Agent Development Kit | E5: YouTube — Google for Developers | F5: HIGH | G5: 0.3 | H5: Understand ADK design goals: model/deployment agnosticism, multi-agent, debugging. | I5: Take notes only on architectural primitives; compare with your own agent loop. | J5: Roadmap | K5: Go to detail | L5: Open resource | M5: Not Started | N5: Architecture comparison notes. | O5: 46296 | P5: 46302
A6: 5 | B6: From Week 1 — 3–5 problems/week in parallel | C6: PARALLEL — CS / Interview | D6: LeetCode 75 | E6: LeetCode | F6: VERY HIGH | H6: Complete if rusty; otherwise use as diagnostic and focus on weak patterns. | I6: Solve without hints; after each problem record pattern, complexity, edge cases, and one alternate solution. | J6: CS + Interview Track | K6: Go to detail | L6: Open resource | M6: Not Started | N6: Google-style engineering interviews still require fast, correct algorithmic reasoning. | O6: 46296 | P6: 46379
A7: 6 | B7: From Week 1 — Parallel refresh | C7: PARALLEL — CS / Interview | D7: MIT 6.006 — Introduction to Algorithms | E7: MIT OpenCourseWare | F7: HIGH | H7: Selective refresh: hashing, graphs, shortest paths, dynamic programming, complexity; do problem sets for weak areas. | I7: Complete 2–3 MIT problem sets from your weakest topics without solutions, then compare. | J7: CS + Interview Track | K7: Go to detail | L7: Open resource | M7: Not Started | N7: Deepens the reasoning behind interview patterns rather than memorizing LeetCode templates. | O7: 46296 | P7: 46351
A8: 7 | B8: From Week 1 — Selective | C8: PARALLEL — CS / Interview | D8: MIT 6.034 — Artificial Intelligence | E8: MIT OpenCourseWare | F8: MEDIUM | H8: Select search, planning, constraints and probabilistic reasoning; skip material duplicated by stronger modern sources. | I8: Implement A*/minimax or a constraint solver and explicitly compare its deterministic search with LLM planning. | J8: CS + Interview Track | K8: Go to detail | L8: Open resource | M8: Not Started | N8: Gives historical/algorithmic grounding for planning and search techniques that reappear in modern agents. | O8: 46296 | P8: 46337
A9: 8 | B9: From Week 1 — Selective / project-driven | C9: PARALLEL — CS / Interview | D9: CS50's Introduction to Artificial Intelligence with Python | E9: Harvard / edX | F9: HIGH | H9: Selective completion recommended for an experienced engineer: search, uncertainty, optimization, learning and language projects. | I9: Complete at least 3 projects from topics where your intuition is weakest; explain algorithmic choices and failure cases. | J9: CS + Interview Track | K9: Go to detail | L9: Open resource | M9: Not Started | N9: Hands-on classical AI and ML fundamentals with real Python projects; good gap detector before deeper research material. | O9: 46296 | P9: 46351
A10: 9 | B10: Week 2 — ADK deep foundation | C10: CORE — Agent Engineering | D10: ADK Training Modules 1–7 | E10: Maurizio Ipsale | F10: VERY HIGH | G10: 4 | H10: Environment, LlmAgent, programmatic runs, model portability, multimodal. | I10: Run every module; rebuild modules 3, 4.5 and 6 without copying. | J10: Roadmap | K10: Go to detail | L10: Open resource | M10: Not Started | N10: Annotated repo fork/branch + lessons.md. | O10: 46303 | P10: 46309
A11: 10 | B11: Week 2 — Tools | C11: CORE — Agent Engineering | D11: Building AI Agents with ADK: Empowering with Tools | E11: Google Codelabs | F11: VERY HIGH | G11: 1.5 | H11: Function tools, built-in search, third-party tools, sub-agents. | I11: Add 3 tools to one agent; write schema/argument edge-case tests. | J11: Roadmap | K11: Go to detail | L11: Open resource | M11: Not Started | N11: Tool contract tests + failure matrix. | O11: 46303 | P11: 46309
A12: 11 | B12: Week 3 — Tools & grounding | C12: CORE — Agent Engineering | D12: ADK Training Modules 8–14 | E12: Maurizio Ipsale | F12: VERY HIGH | G12: 5 | H12: Custom tools, ToolContext, OpenAPI, grounding, HITL, persistence, third-party tools. | I12: Build an agent with stateful tool calls, OpenAPI integration, and an approval gate. | J12: Roadmap | K12: Go to detail | L12: Open resource | M12: Not Started | N12: Repo: tool-rich-agent + test suite. | O12: 46310 | P12: 46316
A13: 12 | B13: Week 3 — Tool engineering | C13: CORE — Agent Engineering | D13: Writing effective tools for agents — with agents | E13: Anthropic Engineering | F13: VERY HIGH | G13: 1 | H13: Design tool interfaces that agents can select and use reliably. | I13: Take one existing tool API; redesign name, description, schema, and output for agent use. A/B eval it. | J13: Roadmap | K13: Go to detail | L13: Open resource | M13: Not Started | N13: Before/after tool eval report. | O13: 46310 | P13: 46316
A14: 13 | B14: Week 3 — Agent patterns | C14: CORE — Agent Engineering | D14: Building more effective AI agents | E14: YouTube — Anthropic | F14: VERY HIGH | G14: 0.4 | H14: Learn simple agent patterns, subagents, skills, MCP and common failure modes. | I14: Implement one pattern without a framework: routing or parallel subagents. | J14: Roadmap | K14: Go to detail | L14: Open resource | M14: Not Started | N14: Small pure-Python pattern repo. | O14: 46310 | P14: 46316
A15: 14 | B15: Weeks 3–5 | C15: PARALLEL — Data / RAG / Graph | D15: Vector Search and Embeddings | E15: Google Skills / GEAR | F15: VERY HIGH | H15: Learn embeddings, semantic search, hybrid retrieval and grounded RAG before adding agent orchestration. | I15: Build a small corpus; compare keyword, vector and hybrid retrieval on a labeled query set. | J15: Data + RAG Track | K15: Go to detail | L15: Open resource | M15: Not Started | N15: Retrieval benchmark with Recall@K / MRR + failure notes | O15: 46310 | P15: 46330
A16: 15 | B16: From Week 3 — 2–3 h/week | C16: PARALLEL — CS / Interview | D16: Grokking Modern System Design Interview | E16: Educative | F16: VERY HIGH | H16: Prioritize distributed-system fundamentals + 8–10 case studies + mock interviews. | I16: Do one 45-minute design from a blank page weekly; record requirements, estimates, API/data model, failure modes and tradeoffs. | J16: CS + Interview Track | K16: Go to detail | L16: Open resource | M16: Not Started | N16: Senior Google/Anthropic roles require architecture tradeoffs, reliability, consistency, capacity, queues, caches and failure handling. | O16: 46310 | P16: 46393
A17: 16 | B17: Week 4 — MCP fundamentals | C17: CORE — Agent Engineering | D17: Model Context Protocol (MCP): Hands-On with Agentic AI | E17: LinkedIn Learning | F17: HIGH | G17: 0.9 | H17: Use MCP clients/servers and build Python/TypeScript MCP servers. | I17: Build a small MCP server, inspect it, then connect it from Claude and one other client. | J17: Roadmap | K17: Go to detail | L17: Open resource | M17: Not Started | N17: Repo: mcp-server-lab. | O17: 46317 | P17: 46323
A18: 17 | B18: Week 4 — MCP in ADK | C18: CORE — Agent Engineering | D18: ADK Training Modules 27–28 | E18: Maurizio Ipsale | F18: VERY HIGH | G18: 1.5 | H18: Build and consume MCP tools with ADK. | I18: Expose one internal service through MCP; add auth/error handling. | J18: Roadmap | K18: Go to detail | L18: Open resource | M18: Not Started | N18: Production-style MCP service skeleton. | O18: 46317 | P18: 46323
A19: 18 | B19: Week 4 — MCP + ADK + A2A | C19: CORE — Agent Engineering | D19: Getting Started with MCP, ADK and A2A | E19: Google Codelabs | F19: VERY HIGH | G19: 2 | H19: Build MCP server, deploy to Cloud Run, use with ADK, expose agent via A2A. | I19: Complete lab, then replace currency tool with your own business domain. | J19: Roadmap | K19: Go to detail | L19: Open resource | M19: Not Started | N19: Cross-protocol architecture diagram + runnable repo. | O19: 46317 | P19: 46323
A20: 19 | B20: Weeks 4–6 | C20: PARALLEL — Data / RAG / Graph | D20: Building Agents with Retrieval-Augmented Generation | E20: Google Codelabs | F20: VERY HIGH | H20: Connect retrieval and structured tools to an ADK agent so the model decides when and how to retrieve. | I20: Complete the financial-analysis lab, then replace one data source with your own corpus/API. | J20: Data + RAG Track | K20: Go to detail | L20: Open resource | M20: Not Started | N20: Agentic-RAG repo + eval set | O20: 46317 | P20: 46337
A21: 20 | B21: Week 5 — MCP efficiency | C21: CORE — Agent Engineering | D21: Code execution with MCP: Building more efficient agents | E21: Anthropic Engineering | F21: VERY HIGH | G21: 0.8 | H21: Understand context cost of tool definitions/results and code-mediated tool use. | I21: Benchmark direct tool calls vs code execution across 20 tasks: tokens, latency, success. | J21: Roadmap | K21: Go to detail | L21: Open resource | M21: Not Started | N21: Benchmark notebook/report. | O21: 46324 | P21: 46330
A22: 21 | B22: Week 5 — MCP deeper dive | C22: CORE — Agent Engineering | D22: Introduction to Model Context Protocol by Anthropic | E22: LinkedIn Learning | F22: HIGH | G22: 1 | H22: Build MCP servers/clients with tools, resources and prompts. | I22: Implement document-management MCP project; add one resource and one prompt primitive. | J22: Roadmap | K22: Go to detail | L22: Open resource | M22: Not Started | N22: MCP primitives reference implementation. | O22: 46324 | P22: 46330
A23: 22 | B23: Week 5 — Multi-agent fundamentals | C23: CORE — Agent Engineering | D23: ADK Training Modules 15–21.5 | E23: Maurizio Ipsale | F23: VERY HIGH | G23: 4.5 | H23: Static/dynamic orchestration, routing, collaboration, cycles, distributed graphs. | I23: Recreate 3 orchestration patterns from memory and compare failure modes. | J23: Roadmap | K23: Go to detail | L23: Open resource | M23: Not Started | N23: Patterns repo + decision matrix. | O23: 46324 | P23: 46330
A24: 23 | B24: Weeks 5–7 | C24: PARALLEL — Data / RAG / Graph | D24: Vertex AI RAG Engine quickstart | E24: Google Cloud | F24: HIGH | H24: Understand production corpus ingestion, managed retrieval, metadata and retrieval APIs. | I24: Create a RAG corpus, ingest documents, retrieve contexts, and instrument latency/cost. | J24: Data + RAG Track | K24: Go to detail | L24: Open resource | M24: Not Started | N24: RAG Engine notebook + architecture note | O24: 46324 | P24: 46344
A25: 24 | B25: Weeks 5–7 | C25: PARALLEL — Data / RAG / Graph | D25: Reranking for Vertex AI RAG Engine | E25: Google Cloud | F25: VERY HIGH | H25: Retrieval quality often dominates answer quality; reranking is a core production technique. | I25: Compare baseline top-K retrieval vs reranked retrieval on at least 30 labeled queries. | J25: Data + RAG Track | K25: Go to detail | L25: Open resource | M25: Not Started | N25: Before/after retrieval metrics + cost/latency | O25: 46324 | P25: 46344
A26: 25 | B26: From Week 5 — 1 topic/week | C26: PARALLEL — CS / Interview | D26: MIT 6.824 — Distributed Computer Systems Engineering | E26: MIT OpenCourseWare | F26: VERY HIGH | H26: Selective deep study: fault tolerance, replication, consistency, distributed storage, naming and failure recovery. | I26: Write design notes applying replication/consistency/failure concepts to an agent runtime, tool service and memory service. | J26: CS + Interview Track | K26: Go to detail | L26: Open resource | M26: Not Started | N26: Agent platforms are distributed systems with stochastic components; these concepts remain foundational even though this OCW edition is older. | O26: 46324 | P26: 46393
A27: 26 | B27: Week 6 — Distributed multi-agent | C27: CORE — Agent Engineering | D27: Architect Multi-Agent Systems with ADK | E27: Google Skills / GEAR | F27: VERY HIGH | G27: 3 | H27: Collaborative workflows, shared state, distributed communication and deployment. | I27: Build a supervisor + 3 specialists with explicit shared-state rules. | J27: Roadmap | K27: Go to detail | L27: Open resource | M27: Not Started | N27: System diagram + orchestration tests. | O27: 46331 | P27: 46337
A28: 27 | B28: Week 6 — A2A | C28: CORE — Agent Engineering | D28: Multi-Agent Systems with Agent2Agent | E28: Google Codelabs | F28: VERY HIGH | G28: 0.75 | H28: Agent Cards, A2A servers, remote connections and host orchestration. | I28: Complete lab; add versioned Agent Card and simulated remote failure. | J28: Roadmap | K28: Go to detail | L28: Open resource | M28: Not Started | N28: A2A contract test suite. | O28: 46331 | P28: 46337
A29: 28 | B29: Week 6 — MCP + A2A cross-vendor | C29: CORE — Agent Engineering | D29: Hands-On AI: MCP and Agent2Agent (A2A) | E29: LinkedIn Learning | F29: HIGH | G29: 1.7 | H29: MCP server/client and multi-agent A2A design/implementation. | I29: Implement HR-style example using a different domain and at least 2 independent processes. | J29: Roadmap | K29: Go to detail | L29: Open resource | M29: Not Started | N29: Interoperability demo. | O29: 46331 | P29: 46337
A30: 29 | B30: Weeks 6–9 | C30: PARALLEL — Data / RAG / Graph | D30: Build a RAG evaluation harness | E30: Self-directed | F30: VERY HIGH | H30: A RAG system needs separate retrieval and generation metrics; end-answer quality alone hides failure causes. | I30: Measure Recall@K/MRR/nDCG, context precision, groundedness, answer relevance and citation correctness. | J30: Data + RAG Track | K30: Go to detail | L30: Open resource | M30: Not Started | N30: Reusable rag-evals package | O30: 46331 | P30: 46358
A31: 30 | B31: Week 7 — Production multi-agent | C31: CORE — Agent Engineering | D31: Build a Multi-Agent Creative Studio with ADK, A2A, MCP | E31: Google Codelabs | F31: VERY HIGH | G31: 3 | H31: Distributed agents on Cloud Run, Agent Runtime, MCP, Skills, quality-control loop, context compaction. | I31: Complete lab; replace creative domain with architecture-review workflow. | J31: Roadmap | K31: Go to detail | L31: Open resource | M31: Not Started | N31: Deployed multi-agent portfolio project v1. | O31: 46338 | P31: 46344
A32: 31 | B32: Week 7 — Multi-agent production lessons | C32: CORE — Agent Engineering | D32: How we built our multi-agent research system | E32: Anthropic Engineering | F32: VERY HIGH | G32: 1 | H32: Learn orchestrator-worker architecture, parallel exploration, eval and reliability lessons. | I32: Clone the pattern for a research task and compare single-agent vs multi-agent cost/quality. | J32: Roadmap | K32: Go to detail | L32: Open resource | M32: Not Started | N32: Experiment report with metrics. | O32: 46338 | P32: 46344
A33: 32 | B33: Weeks 7–9 | C33: PARALLEL — Data / RAG / Graph | D33: Getting started with Spanner Graph | E33: Google Codelabs | F33: HIGH | H33: Learn property graphs, nodes/edges, ISO GQL pattern matching, traversal, and relational/graph interoperability. | I33: Complete the codelab, then model one domain from your capstone as nodes/edges and write 8 GQL queries. | J33: Data + RAG Track | K33: Go to detail | L33: Open resource | M33: Not Started | N33: Graph schema + GQL query pack | O33: 46338 | P33: 46358
A34: 33 | B34: Week 8 — State & memory | C34: CORE — Agent Engineering | D34: ADK Training Modules 22–23 | E34: Maurizio Ipsale | F34: VERY HIGH | G34: 1.5 | H34: State, memory and artifacts for production agents. | I34: Implement session state + cross-session memory + artifact store; document retention rules. | J34: Roadmap | K34: Go to detail | L34: Open resource | M34: Not Started | N34: State/memory design doc + tests. | O34: 46345 | P34: 46351
A35: 34 | B35: Week 8 — Context engineering | C35: CORE — Agent Engineering | D35: Effective context engineering for AI agents | E35: Anthropic Engineering | F35: VERY HIGH | G35: 1 | H35: Treat context as a finite resource; decide what enters, persists, and is retrieved. | I35: Instrument context size; implement compaction/retrieval policy and compare outcomes. | J35: Roadmap | K35: Go to detail | L35: Open resource | M35: Not Started | N35: Context-budget benchmark. | O35: 46345 | P35: 46351
A36: 35 | B36: Weeks 8–11 | C36: PARALLEL — Data / RAG / Graph | D36: GraphRAG infrastructure using Agent Platform and Spanner Graph | E36: Google Cloud Architecture Center | F36: VERY HIGH | H36: GraphRAG combines vector retrieval with graph traversal for relationship-aware, multi-hop context. | I36: Design ingestion + serving architecture; explicitly decide what belongs in vectors, relational columns and graph edges. | J36: Data + RAG Track | K36: Go to detail | L36: Open resource | M36: Not Started | N36: Architecture diagram + ADR | O36: 46345 | P36: 46372
A37: 36 | B37: From Week 8 — 1 design every 1–2 weeks | C37: PARALLEL — CS / Interview | D37: Grokking the Machine Learning System Design Interview | E37: Educative | F37: VERY HIGH | H37: Complete the framework plus LLM/semantic-search/evaluation-related cases; selectively skim familiar ML basics. | I37: Design an LLM/agent platform under explicit latency, cost, eval, safety and rollout constraints. | J37: CS + Interview Track | K37: Go to detail | L37: Open resource | M37: Not Started | N37: Bridges model quality, data, serving, experimentation and production architecture—the exact interface AI architects need. | O37: 46345 | P37: 46407
A38: 37 | B38: Week 9 — Evaluation | C38: CORE — Agent Engineering | D38: ADK Training Module 24 — Evaluation | E38: Maurizio Ipsale | F38: VERY HIGH | G38: 1 | H38: Create reproducible agent evaluations. | I38: Create 30-task golden set; measure task success, tool choice and argument correctness. | J38: Roadmap | K38: Go to detail | L38: Open resource | M38: Not Started | N38: evals/ directory in main project. | O38: 46352 | P38: 46358
A39: 38 | B39: Week 9 — Agent evals | C39: CORE — Agent Engineering | D39: AI Evaluations: Foundations and Practical Examples | E39: LinkedIn Learning | F39: VERY HIGH | G39: 2.1 | H39: Build practical AI/agent evaluation methods. | I39: Add deterministic + LLM-judge graders; manually audit a sample of judge decisions. | J39: Roadmap | K39: Go to detail | L39: Open resource | M39: Not Started | N39: Evaluator calibration report. | O39: 46352 | P39: 46358
A40: 39 | B40: Week 9 — Agent eval methodology | C40: CORE — Agent Engineering | D40: Demystifying evals for AI agents | E40: Anthropic Engineering | F40: VERY HIGH | G40: 1 | H40: Design multi-turn agent evals that grade outcomes and trajectories. | I40: Expand golden set to 100 tasks split easy/medium/hard/adversarial. | J40: Roadmap | K40: Go to detail | L40: Open resource | M40: Not Started | N40: Public benchmark README + failure taxonomy. | O40: 46352 | P40: 46358
A41: 40 | B41: Weeks 9–12 | C41: PARALLEL — Data / RAG / Graph | D41: Build GraphRAG with Spanner Graph and LangChain | E41: Google Cloud | F41: HIGH | H41: See a practical knowledge-graph construction and retrieval flow using vector and graph queries together. | I41: Implement a miniature GraphRAG corpus and compare answers against vector-only RAG. | J41: Data + RAG Track | K41: Go to detail | L41: Open resource | M41: Not Started | N41: RAG vs GraphRAG benchmark | O41: 46352 | P41: 46379
A42: 41 | B42: Week 10 — Observability & callbacks | C42: CORE — Agent Engineering | D42: ADK Training Modules 25–26 | E42: Maurizio Ipsale | F42: VERY HIGH | G42: 1.5 | H42: Observe agent behavior and intercept lifecycle events. | I42: Capture trace spans, tool latency, tokens, retries and errors; create incident walkthrough. | J42: Roadmap | K42: Go to detail | L42: Open resource | M42: Not Started | N42: Trace screenshots + debugging playbook. | O42: 46359 | P42: 46365
A43: 42 | B43: Week 10 — Governance | C43: CORE — Agent Engineering | D43: Governing AI Agents: Visibility and Control | E43: LinkedIn Learning | F43: HIGH | G43: 0.9 | H43: Production observability, guardrails and action logging. | I43: Add policy checks, action audit log and privileged-tool approval. | J43: Roadmap | K43: Go to detail | L43: Open resource | M43: Not Started | N43: Governance controls checklist. | O43: 46359 | P43: 46365
A44: 43 | B44: Week 10 — Failure recovery | C44: CORE — Agent Engineering | D44: Operating AI Agents: Failure and Recovery | E44: LinkedIn Learning | F44: VERY HIGH | G44: 0.7 | H44: Detect, diagnose and recover from agent failures. | I44: Inject timeouts, malformed tool returns, auth errors and partial failures; implement recovery. | J44: Roadmap | K44: Go to detail | L44: Open resource | M44: Not Started | N44: Chaos/failure test report. | O44: 46359 | P44: 46365
A45: 44 | B45: Week 10 — Integrated agent engineering review | C45: CORE — Agent Engineering | D45: 5-Day AI Agents Intensive Course with Google | E45: Kaggle + Google | F45: HIGH | G45: 8 | H45: Consolidate agents, tools, orchestration, memory/context, evals/observability, A2A and production using Google-authored notebooks. | I45: Complete the required notebooks across all five units; then rebuild one notebook locally without Kaggle scaffolding and add your own eval cases. | J45: Roadmap | K45: Go to detail | L45: Open resource | M45: Not Started | N45: Kaggle notebooks + local reproduction repo + synthesis notes. | O45: 46359 | P45: 46365
A46: 45 | B46: Weeks 10–16 | C46: PARALLEL — Data / RAG / Graph | D46: Spanner: Google's Globally-Distributed Database | E46: Google Research | F46: VERY HIGH | H46: Build first-principles intuition for sharding, synchronous replication, external consistency, MVCC and TrueTime. | I46: Write a 2-page systems note mapping Spanner guarantees to agent state, memory, tool transactions and multi-region services. | J46: Data + RAG Track | K46: Go to detail | L46: Open resource | M46: Not Started | N46: Systems-design note | O46: 46359 | P46: 46407
A47: 46 | B47: Weeks 10–16 | C47: PARALLEL — Data / RAG / Graph | D47: TrueTime and external consistency | E47: Google Cloud | F47: HIGH | H47: Strong consistency and transaction ordering become important when autonomous agents mutate shared state. | I47: Design a shared-agent-state scenario; identify anomalies under weaker consistency and how external consistency changes the design. | J47: Data + RAG Track | K47: Go to detail | L47: Open resource | M47: Not Started | N47: Consistency failure analysis | O47: 46359 | P47: 46407
A48: 47 | B48: From Week 10 — Selective / 2–4 problems/week | C48: PARALLEL — CS / Interview | D48: Top Interview 150 | E48: LeetCode | F48: HIGH | H48: Use after LeetCode 75 or selectively for weak topics; do not blindly grind all 150 if already strong. | I48: Weekly 45-minute mock block: 2 problems, explain before coding, test manually, then optimize. | J48: CS + Interview Track | K48: Go to detail | L48: Open resource | M48: Not Started | N48: Broader interview coverage and sustained timed practice. | O48: 46359 | P48: 46435
A49: 48 | B49: Week 11 — Enterprise governance | C49: CORE — Agent Engineering | D49: Deploy an Enterprise Governance-Aware Agent with MCP and Cloud Run | E49: Google Codelabs | F49: VERY HIGH | G49: 2 | H49: Managed MCP, governance skills, IAM and Cloud Run deployment. | I49: Complete lab; remove unauthenticated access and design least-privilege IAM. | J49: Roadmap | K49: Go to detail | L49: Open resource | M49: Not Started | N49: Security review + deployment diagram. | O49: 46366 | P49: 46372
A50: 49 | B50: Week 11 — Containment | C50: CORE — Agent Engineering | D50: How we contain Claude across products | E50: Anthropic Engineering | F50: VERY HIGH | G50: 1.5 | H50: Understand blast-radius reduction, sandboxing, egress and filesystem boundaries. | I50: Threat-model your capstone; implement sandbox/network/file constraints where feasible. | J50: Roadmap | K50: Go to detail | L50: Open resource | M50: Not Started | N50: Threat model + red-team cases. | O50: 46366 | P50: 46372
A51: 50 | B51: Week 12 — Production deployment | C51: CORE — Agent Engineering | D51: Deploy Production Ready Agents | E51: Google Skills / GEAR | F51: VERY HIGH | G51: 5 | H51: Agent lifecycle, Agent Engine/Cloud Run, MCP and A2A production connectivity. | I51: Complete challenge lab; write runbook for deploy/rollback/observe. | J51: Roadmap | K51: Go to detail | L51: Open resource | M51: Not Started | N51: Production runbook + badge. | O51: 46373 | P51: 46379
A52: 51 | B52: Week 12 — Cloud deployment | C52: CORE — Agent Engineering | D52: ADK Training Modules 31–36 | E52: Maurizio Ipsale | F52: VERY HIGH | G52: 4.5 | H52: Cloud Run, GKE, MCP server deployment, Agent Runtime, Gemini Enterprise. | I52: Deploy same agent to Cloud Run and GKE; compare ops/cost/latency tradeoffs. | J52: Roadmap | K52: Go to detail | L52: Open resource | M52: Not Started | N52: Deployment comparison doc. | O52: 46373 | P52: 46379
A53: 52 | B53: Weeks 12–16 | C53: PARALLEL — Data / RAG / Graph | D53: Spanner Graph algorithms overview | E53: Google Cloud | F53: MEDIUM | H53: Centrality, clustering, similarity and path finding matter for entity resolution, recommendation, fraud and graph-assisted retrieval. | I53: Run at least two graph algorithms and show when algorithmic graph signals improve retrieval or ranking. | J53: Data + RAG Track | K53: Go to detail | L53: Open resource | M53: Not Started | N53: Graph-algorithm experiment | O53: 46373 | P53: 46407
A54: 53 | B54: From Week 12 — Selective / ~6 h total | C54: PARALLEL — CS / Interview | D54: Agentic System Design | E54: Educative | F54: HIGH | H54: Use as interview-oriented reinforcement, not as the primary agent course. | I54: Turn 5 scenarios into architecture decision records: agent vs workflow, single vs multi-agent, tool boundary, memory, eval and fallback. | J54: CS + Interview Track | K54: Go to detail | L54: Open resource | M54: Not Started | N54: Useful for practicing how to explain agent components, orchestration, guardrails and human oversight under interview constraints. | O54: 46373 | P54: 46407
A55: 54 | B55: From Week 12 — Optional depth | C55: PARALLEL — CS / Interview | D55: MIT 6.172 — Performance Engineering of Software Systems | E55: MIT OpenCourseWare | F55: HIGH | H55: Selective: profiling, caches, parallelism, synchronization, measurement; prioritize if targeting AI systems/infra roles. | I55: Profile one agent service end-to-end and make a measured performance improvement with before/after evidence. | J55: CS + Interview Track | K55: Go to detail | L55: Open resource | M55: Not Started | N55: Frontier AI engineering increasingly rewards engineers who can reason about latency, throughput, parallelism and compute efficiency. | O55: 46373 | P55: 46414
A56: 55 | B56: Week 13 — Google managed MCP | C56: CORE — Agent Engineering | D56: Build a Location Intelligence ADK Agent with BigQuery & Maps MCP | E56: Google Codelabs | F56: HIGH | G56: 2 | H56: Use two remote Google-managed MCP servers for data + location reasoning. | I56: Complete lab; add one eval for incorrect tool choice and one for cross-tool reasoning. | J56: Roadmap | K56: Go to detail | L56: Open resource | M56: Not Started | N56: Multi-MCP eval cases. | O56: 46380 | P56: 46386
A57: 56 | B57: Week 13 — Agent Skills | C57: CORE — Agent Engineering | D57: Use Agent Skills with Multi-Agent Systems | E57: Google Skills / GEAR | F57: VERY HIGH | G57: 1.75 | H57: Combine ADK Skills, MCP, A2A and Agent Engine. | I57: Package one domain skill and dynamically load/use it in a multi-agent workflow. | J57: Roadmap | K57: Go to detail | L57: Open resource | M57: Not Started | N57: Reusable agent-skill package. | O57: 46380 | P57: 46386
A58: 57 | B58: Week 14 — Plugins, Skills, AgentOps | C58: CORE — Agent Engineering | D58: ADK Training Modules 37–40 | E58: Maurizio Ipsale | F58: VERY HIGH | G58: 4.5 | H58: Capstone, best practices, plugins, agent skills and AgentOps. | I58: Complete advanced capstone but substitute one domain component with your own implementation. | J58: Roadmap | K58: Go to detail | L58: Open resource | M58: Not Started | N58: Capstone v2 + retrospective. | O58: 46387 | P58: 46393
A59: 58 | B59: Week 14 — AI-assisted agent engineering | C59: CORE — Agent Engineering | D59: Coding with AI / Agents CLI | E59: Google ADK Docs | F59: HIGH | G59: 1 | H59: Use coding-agent skills and ADK Docs MCP for scaffold/build/test/eval/deploy. | I59: Use Agents CLI/Claude Code to modify an ADK project; review every generated change. | J59: Roadmap | K59: Go to detail | L59: Open resource | M59: Not Started | N59: Agent-assisted engineering log. | O59: 46387 | P59: 46393
A60: 59 | B60: Week 14 — Dynamic tool discovery | C60: CORE — Agent Engineering | D60: Introducing advanced tool use | E60: Anthropic Engineering | F60: VERY HIGH | G60: 1 | H60: Tool search, deferred loading, programmatic tool calling. | I60: Create 30+ mock tools; measure context/tool-selection performance with eager vs dynamic discovery. | J60: Roadmap | K60: Go to detail | L60: Open resource | M60: Not Started | N60: Tool-scaling benchmark. | O60: 46387 | P60: 46393
A61: 60 | B61: From Week 14 — research depth | C61: PARALLEL — Frontier Research | D61: Scaling Intelligence Lab — Research Themes | E61: Stanford | F61: VERY HIGH | H61: The lab explicitly focuses on scalable/self-improving AI, agentic optimization, automated verifiers/benchmarks, and AI systems. | I61: Use as an ongoing research radar; maintain a one-page map of themes and how your projects connect. | J61: Stanford Research Track | K61: Go to detail | L61: Open resource | M61: Not Started | N61: Research map | O61: 46387 | P61: 46435
A62: 61 | B62: From Week 14 — research depth | C62: PARALLEL — Frontier Research | D62: Scaling Intelligence Lab — Publications | E62: Stanford | F62: VERY HIGH | H62: A concentrated feed of recent work directly relevant to frontier agent engineering. | I62: Read one paper/week during the advanced phase; reproduce or ablate at least one. | J62: Stanford Research Track | K62: Go to detail | L62: Open resource | M62: Not Started | N62: Paper notes + one replication | O62: 46387 | P62: 46435
A63: 62 | B63: From Week 14 — research depth | C63: PARALLEL — Frontier Research | D63: Aakanksha Chowdhery — Research Site | E63: Aakanksha Chowdhery | F63: HIGH | H63: Useful ongoing feed for self-improving agents, RL, reasoning and systems research; also co-instructor context for CS329A. | I63: Check quarterly, not weekly; pull only papers/talks that create a concrete experiment or design question. | J63: Stanford Research Track | K63: Go to detail | L63: Open resource | M63: Not Started | N63: Research watch notes | O63: 46387 | P63: 46435
A64: 63 | B64: Week 15 — Long-running agents | C64: CORE — Agent Engineering | D64: Effective harnesses for long-running agents | E64: Anthropic Engineering | F64: VERY HIGH | G64: 1 | H64: Design continuity across context windows and sessions. | I64: Build a two-session coding/research task with handoff notes, progress state and recovery. | J64: Roadmap | K64: Go to detail | L64: Open resource | M64: Not Started | N64: Long-running harness prototype. | O64: 46394 | P64: 46400
A65: 64 | B65: Week 15 — Current Google agent engineering intensive | C65: CORE — Agent Engineering | D65: 5-Day AI Agents: Intensive Vibe Coding Course with Google (2026) | E65: Kaggle + Google | F65: VERY HIGH | G65: 10 | H65: Practice the current Google agent workflow: agent skills, Agents CLI, tools/protocols, security/evaluation, and spec-driven production development. | I65: Complete the codelabs and capstone-style project; demonstrate at least three advanced concepts and publish architecture, eval, and failure-analysis notes. | J65: Roadmap | K65: Go to detail | L65: Open resource | M65: Not Started | N65: Kaggle capstone artifact + GitHub repo + short demo + technical retrospective. | O65: 46394 | P65: 46400
A66: 65 | B66: Week 15 — Self-improving agents / research depth | C66: CORE — Agent Engineering | D66: Stanford CS329A — Self-Improving AI Agents | E66: Stanford | F66: VERY HIGH | G66: 24 | H66: Understand frontier techniques for self-improving agents: test-time scaling, verifiers, RL, tool/code feedback, planning, memory, long-horizon evaluation, and agentic software engineering. | I66: Follow the lecture sequence selectively; read the core papers; reproduce one result or ablation from a CS329A topic on a small benchmark rather than only taking notes. | J66: Roadmap | K66: Go to detail | L66: Open resource | M66: Not Started | N66: Research-replication repo + 4–6 page technical report with hypothesis, method, results, ablations, failures, and next steps. | O66: 46394 | P66: 46400
A67: 66 | B67: Week 15 — Cross-framework breadth | C67: CORE — Agent Engineering | D67: AI Engineer Agentic Track: Complete Agent & MCP Course | E67: Udemy | F67: HIGH | G67: 21.1 | H67: Compare OpenAI Agents SDK, CrewAI, LangGraph, AutoGen and MCP through projects. | I67: Do not complete blindly: select 3 projects and reimplement one using ADK. | J67: Roadmap | K67: Go to detail | L67: Open resource | M67: Not Started | N67: Framework comparison matrix + 3 project commits. | O67: 46394 | P67: 46400
A68: 67 | B68: From Week 15 — research depth | C68: PARALLEL — Frontier Research | D68: CS329A Past Projects | E68: Stanford | F68: VERY HIGH | H68: Provides concrete examples of the research bar: AppBench, PRIME, meta-agents, ARCHON extensions, reasoning/RL and multi-agent verification. | I68: Review 5 projects; score each on novelty, experimental design, baselines, eval rigor and presentation. Use the best as a capstone-quality benchmark. | J68: Stanford Research Track | K68: Go to detail | L68: Open resource | M68: Not Started | N68: Project-review rubric + capstone standard | O68: 46394 | P68: 46407
A69: 68 | B69: From Week 15 — research depth | C69: PARALLEL — Frontier Research | D69: LLM-as-a-Verifier: A General-Purpose Verification Framework | E69: Scaling Intelligence, 2026 | F69: VERY HIGH | H69: Verification is a core bottleneck for self-improving and long-horizon agents. | I69: Build a small verifier benchmark: correctness, false accept/reject, calibration and cost across two models. | J69: Stanford Research Track | K69: Go to detail | L69: Open resource | M69: Not Started | N69: Verifier benchmark report | O69: 46394 | P69: 46407
A70: 69 | B70: Week 16 — Architecture patterns | C70: CORE — Agent Engineering | D70: Agentic AI Architectures with Patterns, Frameworks and MCP | E70: Udemy | F70: HIGH | G70: 7.5 | H70: Agent patterns, orchestration/choreography, MCP/A2A, context engineering and enterprise lifecycle. | I70: Create a pattern decision tree for 8 scenarios; defend single vs multi-agent choices. | J70: Roadmap | K70: Go to detail | L70: Open resource | M70: Not Started | N70: Architecture decision record pack. | O70: 46401 | P70: 46407
A71: 70 | B71: Week 16 — Cross-vendor developer path | C71: CORE — Agent Engineering | D71: Building Agentic AI Systems for Developers | E71: LinkedIn Learning | F71: HIGH | G71: 16 | H71: LangChain/HF, AutoGen, RAG, MCP/A2A, evals, governance and recovery. | I71: Use only modules filling gaps; reproduce key exercise using ADK or pure Python. | J71: Roadmap | K71: Go to detail | L71: Open resource | M71: Not Started | N71: Gap-closure notes. | O71: 46401 | P71: 46407
A72: 71 | B72: From Week 16 — 1 mock/week late in plan | C72: PARALLEL — CS / Interview | D72: AI System Design Interview Questions | E72: Educative | F72: HIGH | H72: Use after system/ML design foundations; emphasize LLM serving, semantic search, safe fallbacks and observability. | I72: Run timed mocks; after each, write what you missed and a better second-pass design. | J72: CS + Interview Track | K72: Go to detail | L72: Open resource | M72: Not Started | N72: Converts broad architecture knowledge into interview-speed reasoning. | O72: 46401 | P72: 46435
A73: 72 | B73: From Week 16 — research depth | C73: PARALLEL — Frontier Research | D73: Decentralized Multi-Agent Systems with Shared Context | E73: Scaling Intelligence, 2026 | F73: VERY HIGH | H73: Directly relevant to multi-agent coordination and shared-context design beyond hierarchical supervisors. | I73: Compare centralized coordinator vs decentralized/shared-context architecture on the same task set. | J73: Stanford Research Track | K73: Go to detail | L73: Open resource | M73: Not Started | N73: Architecture + benchmark | O73: 46401 | P73: 46414
A74: 73 | B74: From Week 16 — research depth | C74: PARALLEL — Frontier Research | D74: Weaver: Shrinking the Generation–Verification Gap with Weak Verifiers | E74: Scaling Intelligence, 2025 | F74: VERY HIGH | H74: Shows why verifier quality can limit self-improvement and how weak-verifier regimes behave. | I74: Reproduce a weak-vs-strong verifier comparison on a compact dataset. | J74: Stanford Research Track | K74: Go to detail | L74: Open resource | M74: Not Started | N74: Ablation report | O74: 46401 | P74: 46414
A75: 74 | B75: From Week 16 — research depth | C75: PARALLEL — Frontier Research | D75: SPRINT: Interleaved Planning and Parallelized Execution | E75: Scaling Intelligence, 2025 | F75: VERY HIGH | H75: Closely aligned with scalable agent planning/execution and latency-aware orchestration. | I75: Implement sequential plan-execute vs interleaved/parallel execution; compare success, latency and token cost. | J75: Stanford Research Track | K75: Go to detail | L75: Open resource | M75: Not Started | N75: Planning benchmark | O75: 46401 | P75: 46414
A76: 75 | B76: Week 17 — Agentic coding | C76: CORE — Agent Engineering | D76: Claude Code: Best practices for agentic coding | E76: Anthropic Engineering | F76: VERY HIGH | G76: 1 | H76: Use low-level coding agents effectively with context, permissions, tests and workflows. | I76: Create CLAUDE.md for your capstone; run plan→implement→test→review workflow. | J76: Roadmap | K76: Go to detail | L76: Open resource | M76: Not Started | N76: CLAUDE.md + coding-agent workflow doc. | O76: 46408 | P76: 46414
A77: 76 | B77: Week 17 — Agentic coding practice | C77: CORE — Agent Engineering | D77: Claude Code best practices | Code w/ Claude | E77: YouTube — Anthropic | F77: HIGH | G77: 0.8 | H77: See practical Claude Code workflows from Anthropic engineering. | I77: Apply 3 techniques to an existing repo and quantify cycle-time/quality impact. | J77: Roadmap | K77: Go to detail | L77: Open resource | M77: Not Started | N77: Before/after engineering notes. | O77: 46408 | P77: 46414
A78: 77 | B78: Week 17 — ADK practical overview | C78: CORE — Agent Engineering | D78: Getting started with Agent Development Kit | E78: YouTube — Google for Developers | F78: MEDIUM | G78: 0.2 | H78: Quick refresher on tools, MCP, deployment and observability. | I78: Watch after hands-on work; list anything the video simplifies or omits. | J78: Roadmap | K78: Go to detail | L78: Open resource | M78: Not Started | N78: Critical-review notes. | O78: 46408 | P78: 46414
A79: 78 | B79: Week 17 — Protocols overview | C79: CORE — Agent Engineering | D79: How to build an AI agent with MCP, ADK, and A2A on Google Cloud | E79: YouTube — Google for Developers | F79: HIGH | G79: 0.25 | H79: End-to-end visual walkthrough of MCP + ADK + A2A architecture. | I79: Redraw architecture from memory and annotate trust boundaries. | J79: Roadmap | K79: Go to detail | L79: Open resource | M79: Not Started | N79: Annotated architecture diagram. | O79: 46408 | P79: 46414
A80: 79 | B80: From Week 17 — research depth | C80: PARALLEL — Frontier Research | D80: CodeMonkeys: Scaling Test-Time Compute for Software Engineering | E80: Scaling Intelligence, 2025 | F80: VERY HIGH | H80: Connects coding agents, inference-time compute and software-engineering benchmarks. | I80: Run a small coding benchmark varying sampling/test-time budget; plot pass rate vs cost. | J80: Stanford Research Track | K80: Go to detail | L80: Open resource | M80: Not Started | N80: Cost-quality curve + analysis | O80: 46408 | P80: 46421
A81: 80 | B81: From Week 17 — research depth | C81: PARALLEL — Frontier Research | D81: Archon: Architecture Search for Inference-Time Techniques | E81: Scaling Intelligence, 2024 | F81: VERY HIGH | H81: A useful bridge from manually designed agent workflows to automated inference architecture search. | I81: Implement 3 inference architectures (single, critic/ranker, planner+critic) and compare quality/cost. | J81: Stanford Research Track | K81: Go to detail | L81: Open resource | M81: Not Started | N81: Architecture-search mini study | O81: 46408 | P81: 46421
A82: 81 | B82: Week 18 — Framework-free mastery | C82: CORE — Agent Engineering | D82: Build a minimal agent runtime from scratch | E82: Self-directed | F82: VERY HIGH | G82: 12 | H82: Internalize agent loop, tools, state, planner/router, retries, tracing and eval hooks. | I82: Implement 2k–4k LOC Python runtime with tests; no LangChain/ADK/CrewAI runtime. | J82: Roadmap | K82: Go to detail | L82: — | M82: Not Started | N82: Repo: agent-runtime-from-scratch. | O82: 46415 | P82: 46421
A83: 82 | B83: From Week 18 — research depth | C83: PARALLEL — Frontier Research | D83: TRACE: Capability-Targeted Agentic Training | E83: Scaling Intelligence, 2026 | F83: HIGH | H83: Pushes beyond prompting/frameworks into training agents for targeted capabilities. | I83: Write an experiment design for one capability (tool use, recovery, planning); if compute permits, run a small-scale version. | J83: Stanford Research Track | K83: Go to detail | L83: Open resource | M83: Not Started | N83: Experiment proposal/results | O83: 46415 | P83: 46428
A84: 83 | B84: Week 19 — Interoperability | C84: CORE — Agent Engineering | D84: Agent protocol lab | E84: Self-directed | F84: VERY HIGH | G84: 8 | H84: Prove MCP/A2A and vendor interoperability. | I84: ADK coordinator + Claude-backed worker + pure Python worker; MCP tools; A2A communication. | J84: Roadmap | K84: Go to detail | L84: — | M84: Not Started | N84: Repo: agent-protocol-lab. | O84: 46422 | P84: 46428
A85: 84 | B85: Week 19 — Benchmarking | C85: CORE — Agent Engineering | D85: Agent eval benchmark | E85: Self-directed | F85: VERY HIGH | G85: 8 | H85: Compare agent architectures using measurable quality/cost/latency/reliability. | I85: Run 100-task benchmark across single/multi-agent and at least 2 model stacks. | J85: Roadmap | K85: Go to detail | L85: — | M85: Not Started | N85: Repo: agent-evals + results dashboard. | O85: 46422 | P85: 46428
A86: 85 | B86: Week 20 — Production capstone | C86: CORE — Agent Engineering | D86: Production multi-agent architecture system | E86: Self-directed | F86: VERY HIGH | G86: 16 | H86: Integrate architecture, protocols, evals, security, ops and deployment. | I86: Deploy a real multi-agent system with auth, persistence, evals, traces, HITL and CI/CD. | J86: Roadmap | K86: Go to detail | L86: — | M86: Not Started | N86: Flagship public/private portfolio repo + architecture paper. | O86: 46429 | P86: 46435
A87: 86 | B87: Week 20 — Technical communication | C87: CORE — Agent Engineering | D87: Publish technical write-up | E87: Self-directed | F87: VERY HIGH | G87: 4 | H87: Demonstrate senior-level reasoning, tradeoffs and clarity. | I87: Write: 'MCP vs A2A vs Agent Skills in production' using your measured examples. | J87: Roadmap | K87: Go to detail | L87: — | M87: Not Started | N87: Public article / internal whitepaper. | O87: 46429 | P87: 46435

Sheet Dashboard
A1: Agentic AI Mastery — Study & Portfolio Tracker
A3: Goal: Google / Anthropic-level agent engineering depth — courses are inputs; code, evals, production and technical reasoning are the outputs. | B3: Goal: Google / Anthropic-level agent engineering depth — courses are inputs; code, evals, production and technical reasoning are the outputs. | C3: Goal: Google / Anthropic-level agent engineering depth — courses are inputs; code, evals, production and technical reasoning are the outputs. | D3: Goal: Google / Anthropic-level agent engineering depth — courses are inputs; code, evals, production and technical reasoning are the outputs. | E3: Goal: Google / Anthropic-level agent engineering depth — courses are inputs; code, evals, production and technical reasoning are the outputs. | F3: Goal: Google / Anthropic-level agent engineering depth — courses are inputs; code, evals, production and technical reasoning are the outputs. | G3: Goal: Google / Anthropic-level agent engineering depth — courses are inputs; code, evals, production and technical reasoning are the outputs. | H3: Goal: Google / Anthropic-level agent engineering depth — courses are inputs; code, evals, production and technical reasoning are the outputs.
A5: KPI | B5: Value | D5: Hands-On KPI | E5: Value | G5: Readiness KPI | H5: Value
A6: Roadmap items | B6: =COUNTA(Roadmap!E2:E100) -> 53 | D6: Labs | E6: =COUNTA('Hands-On Labs'!B2:B50) -> 18 | G6: Overall competency readiness | H6: =AVERAGE('Competency Matrix'!E2:E26) -> 0
A7: Completed | B7: =COUNTIF(Roadmap!M2:M100,"Done") -> 1 | D7: Labs completed | E7: =COUNTIF('Hands-On Labs'!I2:I50,"Done") -> 0 | G7: Competencies at target | H7: =COUNTIF('Competency Matrix'!O2:O26,0) -> 0
A8: VERY HIGH priority items | B8: =COUNTIF(Roadmap!H2:H100,"VERY HIGH") -> 39 | D8: Capstone labs | E8: =COUNTIF('Hands-On Labs'!C2:C50,"Capstone") -> 1 | G8: Program end | H8: 46435
A9: Planned learning hours | B9: =SUM(Roadmap!I2:I100) -> 205.65 | D9: Planned lab hours | E9: =SUM('Hands-On Labs'!H2:H50) -> 147
D10: Link audit | E10: Platform Library re-audited Sep 5, 2026: 62/62 destinations validated; no confirmed broken links. All rows now have an explicit native clickable Open Link plus a copyable URL and audit note. | G10: =HYPERLINK("#'Revision'!A1","Revision / Refresh Guide") -> Revision / Refresh Guide
A12: Provider | B12: Roadmap Items | D12: Status | E12: Count
A13: Google Skills / GEAR | B13: =COUNTIF(Roadmap!F2:F100,A13) -> 5 | D13: Not Started | E13: =COUNTIF(Roadmap!M2:M100,D13) -> 52
A14: Google Codelabs | B14: =COUNTIF(Roadmap!F2:F100,A14) -> 7 | D14: In Progress | E14: =COUNTIF(Roadmap!M2:M100,D14) -> 0
A15: Maurizio Ipsale | B15: =COUNTIF(Roadmap!F2:F100,A15) -> 9 | D15: Done | E15: =COUNTIF(Roadmap!M2:M100,D15) -> 1
A16: Anthropic Engineering | B16: =COUNTIF(Roadmap!F2:F100,A16) -> 9 | D16: Skipped | E16: =COUNTIF(Roadmap!M2:M100,D16) -> 0
A17: LinkedIn Learning | B17: =COUNTIF(Roadmap!F2:F100,A17) -> 7
A18: Udemy | B18: =COUNTIF(Roadmap!F2:F100,A18) -> 2
A19: YouTube — Anthropic | B19: =COUNTIF(Roadmap!F2:F100,A19) -> 2 | D19: Operating Rule | E19: What it means
A20: YouTube — Google for Developers | B20: =COUNTIF(Roadmap!F2:F100,A20) -> 3 | D20: 30 / 70 | E20: ~30% courses/reading; ~70% building, breaking, measuring, deploying.
A21: Kaggle + Google | B21: =COUNTIF(Roadmap!F2:F100,A21) -> 2 | D21: Rebuild from memory | E21: After guided labs, close the instructions and reproduce the core design.
A22: Google ADK Docs | B22: =COUNTIF(Roadmap!F2:F100,A22) -> 1 | D22: Evals before claims | E22: Never call an agent 'good' without a repeatable task set and metrics.
A23: Self-directed | B23: =COUNTIF(Roadmap!F2:F100,A23) -> 5 | D23: Protocol > framework | E23: Be able to explain and implement MCP/A2A concepts outside ADK.
D24: Portfolio > badge count | E24: Four excellent repos with measured tradeoffs beat dozens of tutorial repos.
A25: Stanford | B25: =COUNTIF(Roadmap!F2:F100,A25) -> 1 | D25: Parallel interview track | E25: Run CS + Interview Track at ~3–5 h/week alongside the 20-week agent roadmap; do not replace build/eval/deployment time with interview grinding.
D26: Master navigation | E26: Use Master Plan as the canonical sequence; every item links to its detail sheet and external source.
D27: Program dates | E27: Oct 1, 2026 → Feb 17, 2027 (20 seven-day study blocks).
D28: Competency matrix | E28: Use Current Level 0–4 to turn course completion into measurable readiness and evidence gaps.

Sheet Roadmap
A1: Stage | B1: Order | C1: Week | D1: Topic | E1: Resource | F1: Provider | G1: Type | H1: Priority | I1: Est. Hours | J1: Target Outcome | K1: Hands-on Proof | L1: Portfolio Evidence | M1: Status | N1: Back to Master Plan
A2: 1 | B2: 1 | C2: 1 | D2: Agent fundamentals | E2: Build Agents with Agent Development Kit (ADK) | F2: Google Skills / GEAR | G2: Course | H2: VERY HIGH | I2: 0.5 | J2: Understand ADK's code-first agent model and core abstractions. | K2: Sketch an agent loop and map ADK Agent/Tool/Session concepts onto it. | L2: 1-page architecture note: 'What ADK abstracts vs what it does not'. | M2: Done | N2: https://www.skills.google/course_templates/1585
A3: 1 | B3: 2 | C3: 1 | D3: First ADK agent | E3: Build Your First Agent with ADK | F3: Google Skills / GEAR | G3: Hands-on course | H3: VERY HIGH | I3: 1 | J3: Create, configure, and run ADK agents in Python/YAML. | K3: Build the lab, close instructions, then recreate from memory with one custom behavior. | L3: Repo: first-adk-agent + README + run instructions. | M3: Not Started | N3: https://partner.skills.google/course_templates/1563
A4: 1 | B4: 3 | C4: 1 | D4: ADK foundations | E4: Building AI Agents with ADK: The Foundation | F4: Google Codelabs | G4: Codelab | H4: VERY HIGH | I4: 1 | J4: Set up ADK and build a foundational conversational agent. | K4: Complete codelab, then add structured output and one failure test. | L4: Commit tagged foundation-v1 with tests. | M4: Not Started | N4: https://codelabs.developers.google.com/devsite/codelabs/build-agents-with-adk-foundation
A5: 1 | B5: 4 | C5: 1 | D5: ADK mental model | E5: Introducing Agent Development Kit | F5: YouTube — Google for Developers | G5: Video | H5: HIGH | I5: 0.3 | J5: Understand ADK design goals: model/deployment agnosticism, multi-agent, debugging. | K5: Take notes only on architectural primitives; compare with your own agent loop. | L5: Architecture comparison notes. | M5: Not Started | N5: https://www.youtube.com/watch?v=zgrOwow_uTQ
A6: 1 | B6: 5 | C6: 2 | D6: ADK deep foundation | E6: ADK Training Modules 1–7 | F6: Maurizio Ipsale | G6: Hands-on modules | H6: VERY HIGH | I6: 4 | J6: Environment, LlmAgent, programmatic runs, model portability, multimodal. | K6: Run every module; rebuild modules 3, 4.5 and 6 without copying. | L6: Annotated repo fork/branch + lessons.md. | M6: Not Started | N6: https://mauripsale.github.io/doc-adk-training/docs/
A7: 2 | B7: 6 | C7: 2 | D7: Tools | E7: Building AI Agents with ADK: Empowering with Tools | F7: Google Codelabs | G7: Codelab | H7: VERY HIGH | I7: 1.5 | J7: Function tools, built-in search, third-party tools, sub-agents. | K7: Add 3 tools to one agent; write schema/argument edge-case tests. | L7: Tool contract tests + failure matrix. | M7: Not Started | N7: https://codelabs.developers.google.com/devsite/codelabs/build-agents-with-adk-empowering-with-tools
A8: 2 | B8: 7 | C8: 3 | D8: Tools & grounding | E8: ADK Training Modules 8–14 | F8: Maurizio Ipsale | G8: Hands-on modules | H8: VERY HIGH | I8: 5 | J8: Custom tools, ToolContext, OpenAPI, grounding, HITL, persistence, third-party tools. | K8: Build an agent with stateful tool calls, OpenAPI integration, and an approval gate. | L8: Repo: tool-rich-agent + test suite. | M8: Not Started | N8: https://github.com/mauripsale/doc-adk-training
A9: 2 | B9: 8 | C9: 3 | D9: Tool engineering | E9: Writing effective tools for agents — with agents | F9: Anthropic Engineering | G9: Article | H9: VERY HIGH | I9: 1 | J9: Design tool interfaces that agents can select and use reliably. | K9: Take one existing tool API; redesign name, description, schema, and output for agent use. A/B eval it. | L9: Before/after tool eval report. | M9: Not Started | N9: https://www.anthropic.com/engineering/writing-tools-for-agents
A10: 2 | B10: 9 | C10: 3 | D10: Agent patterns | E10: Building more effective AI agents | F10: YouTube — Anthropic | G10: Video | H10: VERY HIGH | I10: 0.4 | J10: Learn simple agent patterns, subagents, skills, MCP and common failure modes. | K10: Implement one pattern without a framework: routing or parallel subagents. | L10: Small pure-Python pattern repo. | M10: Not Started | N10: https://www.youtube.com/watch?v=uhJJgc-0iTQ
A11: 3 | B11: 10 | C11: 4 | D11: MCP fundamentals | E11: Model Context Protocol (MCP): Hands-On with Agentic AI | F11: LinkedIn Learning | G11: Course | H11: HIGH | I11: 0.9 | J11: Use MCP clients/servers and build Python/TypeScript MCP servers. | K11: Build a small MCP server, inspect it, then connect it from Claude and one other client. | L11: Repo: mcp-server-lab. | M11: Not Started | N11: https://www.linkedin.com/learning/model-context-protocol-mcp-hands-on-with-agentic-ai
A12: 3 | B12: 11 | C12: 4 | D12: MCP in ADK | E12: ADK Training Modules 27–28 | F12: Maurizio Ipsale | G12: Hands-on modules | H12: VERY HIGH | I12: 1.5 | J12: Build and consume MCP tools with ADK. | K12: Expose one internal service through MCP; add auth/error handling. | L12: Production-style MCP service skeleton. | M12: Not Started | N12: https://mauripsale.github.io/doc-adk-training/docs/
A13: 3 | B13: 12 | C13: 4 | D13: MCP + ADK + A2A | E13: Getting Started with MCP, ADK and A2A | F13: Google Codelabs | G13: Codelab | H13: VERY HIGH | I13: 2 | J13: Build MCP server, deploy to Cloud Run, use with ADK, expose agent via A2A. | K13: Complete lab, then replace currency tool with your own business domain. | L13: Cross-protocol architecture diagram + runnable repo. | M13: Not Started | N13: https://codelabs.developers.google.com/codelabs/currency-agent
... A49: 11 | B49: 48 | C49: 17 | D49: Protocols overview | E49: How to build an AI agent with MCP, ADK, and A2A on Google Cloud | F49: YouTube — Google for Developers | G49: Video | H49: HIGH | I49: 0.25 | J49: End-to-end visual walkthrough of MCP + ADK + A2A architecture. | K49: Redraw architecture from memory and annotate trust boundaries. | L49: Annotated architecture diagram. | M49: Not Started | N49: https://www.youtube.com/watch?v=6mQwHqK1I5w
A50: 12 | B50: 49 | C50: 18 | D50: Framework-free mastery | E50: Build a minimal agent runtime from scratch | F50: Self-directed | G50: Capstone lab | H50: VERY HIGH | I50: 12 | J50: Internalize agent loop, tools, state, planner/router, retries, tracing and eval hooks. | K50: Implement 2k–4k LOC Python runtime with tests; no LangChain/ADK/CrewAI runtime. | L50: Repo: agent-runtime-from-scratch. | M50: Not Started
A51: 12 | B51: 50 | C51: 19 | D51: Interoperability | E51: Agent protocol lab | F51: Self-directed | G51: Capstone lab | H51: VERY HIGH | I51: 8 | J51: Prove MCP/A2A and vendor interoperability. | K51: ADK coordinator + Claude-backed worker + pure Python worker; MCP tools; A2A communication. | L51: Repo: agent-protocol-lab. | M51: Not Started
A52: 12 | B52: 51 | C52: 19 | D52: Benchmarking | E52: Agent eval benchmark | F52: Self-directed | G52: Capstone lab | H52: VERY HIGH | I52: 8 | J52: Compare agent architectures using measurable quality/cost/latency/reliability. | K52: Run 100-task benchmark across single/multi-agent and at least 2 model stacks. | L52: Repo: agent-evals + results dashboard. | M52: Not Started
A53: 12 | B53: 52 | C53: 20 | D53: Production capstone | E53: Production multi-agent architecture system | F53: Self-directed | G53: Portfolio capstone | H53: VERY HIGH | I53: 16 | J53: Integrate architecture, protocols, evals, security, ops and deployment. | K53: Deploy a real multi-agent system with auth, persistence, evals, traces, HITL and CI/CD. | L53: Flagship public/private portfolio repo + architecture paper. | M53: Not Started
A54: 12 | B54: 53 | C54: 20 | D54: Technical communication | E54: Publish technical write-up | F54: Self-directed | G54: Writing | H54: VERY HIGH | I54: 4 | J54: Demonstrate senior-level reasoning, tradeoffs and clarity. | K54: Write: 'MCP vs A2A vs Agent Skills in production' using your measured examples. | L54: Public article / internal whitepaper. | M54: Not Started

Sheet Hands-On Labs
A1: # | B1: Lab | C1: Focus | D1: Activity | E1: Acceptance Criteria | F1: Evidence / Repo | G1: Target Week | H1: Est. Hours | I1: Status | K1: Back to Master Plan
A2: 1 | B2: First ADK Agent | C2: Foundations | D2: Build from memory after GEAR/codelab; add structured output + custom tool. | E2: Runs locally; README; tests 3 happy/3 failure cases; no tutorial copy-paste. | F2: first-adk-agent | G2: 1 | H2: 3 | I2: Not Started
A3: 2 | B3: Tool Contract Lab | C3: Tools | D3: Create 5 tools with typed schemas; deliberately create bad descriptions, then improve them. | E3: Measure tool-selection and argument accuracy before/after across 20 prompts. | F3: tool-contract-evals | G3: 3 | H3: 4 | I3: Not Started
A4: 3 | B4: MCP Server | C4: MCP | D4: Expose a real internal-style service via MCP with tools/resources/prompts. | E4: MCP inspector passes; auth/error paths tested; works with 2 clients. | F4: mcp-server-lab | G4: 4 | H4: 6 | I4: Not Started
A5: 4 | B5: MCP Efficiency Benchmark | C5: MCP / Context | D5: Compare direct tool calls vs code execution/dynamic tool discovery. | E5: Report success, tokens, latency, and context size on >=20 tasks. | F5: mcp-efficiency-benchmark | G5: 5 | H5: 5 | I5: Not Started
A6: 5 | B6: A2A Interop Lab | C6: A2A | D6: Build two agents as independent services with Agent Cards and A2A. | E6: Remote call works; version mismatch + timeout cases tested. | F6: a2a-interop-lab | G6: 6 | H6: 6 | I6: Not Started
A7: 6 | B7: Multi-Agent Pattern Pack | C7: Multi-agent | D7: Implement supervisor, router, parallel workers, critique/revision. | E7: Each pattern has tests + decision criteria + known failure modes. | F7: multi-agent-patterns | G7: 6 | H7: 8 | I7: Not Started
A8: 7 | B8: Cross-Vendor Agent Team | C8: Interop | D8: ADK coordinator + Claude-backed agent + pure-Python agent; MCP tools. | E8: Agents collaborate over explicit protocol boundary; vendor swap documented. | F8: cross-vendor-agent-team | G8: 7 | H8: 10 | I8: Not Started
A9: 8 | B9: Memory & Context Lab | C9: Memory | D9: Session state, persistent memory, artifacts, context compaction. | E9: Retention rules documented; context size instrumented; recovery tested. | F9: agent-memory-context | G9: 8 | H9: 6 | I9: Not Started
A10: 9 | B10: 100-Task Eval Harness | C10: Evals | D10: Build golden dataset and graders for task outcome, tool choice, args, trajectory. | E10: 100 tasks; difficulty labels; deterministic + judge graders; manual audit sample. | F10: agent-evals | G10: 9 | H10: 12 | I10: Not Started
A11: 10 | B11: Agent Observability | C11: AgentOps | D11: Instrument traces, tokens, latency, retries, tool errors, routing. | E11: Can diagnose 5 injected failures from traces alone. | F11: agent-observability | G11: 10 | H11: 6 | I11: Not Started
A12: 11 | B12: Agent Red Team | C12: Security | D12: Prompt injection, poisoned tool output, exfiltration, privilege escalation, cost loop. | E12: Threat model + mitigations; repeat attacks after fixes. | F12: agent-red-team | G12: 11 | H12: 8 | I12: Not Started
A13: 12 | B13: Cloud Run / GKE Deployment | C13: Production | D13: Deploy same agent stack to Cloud Run and GKE. | E13: Runbook, rollback, auth, secret handling, cost/ops comparison. | F13: agent-deployment-lab | G13: 12 | H13: 10 | I13: Not Started
... A17: 16 | B17: Technical Article | C17: Communication | D17: Write a measured engineering article: MCP vs A2A vs Agent Skills. | E17: Uses your own code/results; diagrams; tradeoff table; reproducible examples. | F17: Published article / whitepaper | G17: 20 | H17: 4 | I17: Not Started
A18: 17 | B18: RAG Retrieval Quality Benchmark | C18: Core | D18: Build and measure a production-style retrieval pipeline before adding agent complexity. | E18: Create a labeled corpus/query set; compare keyword, vector, hybrid and reranked retrieval. Add chunking and metadata-filter ablations. | F18: Repo + Recall@K/MRR/nDCG table + latency/cost + failure taxonomy | G18: VERY HIGH | H18: 10 | I18: Not Started
A19: 18 | B19: RAG vs GraphRAG / Spanner Graph | C19: Advanced | D19: Determine when relationship-aware retrieval materially outperforms vector-only RAG. | E19: Build the same domain in vector RAG and Spanner Graph GraphRAG. Test multi-hop questions, entity relations and ambiguous queries. | F19: Benchmark + architecture ADR + graph schema + demo | G19: VERY HIGH | H19: 12 | I19: Not Started

Sheet Platform Library
A1: Provider | B1: Resource | C1: Format / Duration | D1: Use | E1: Open Link | F1: Canonical URL | G1: Back to Master Plan | H1: Validation | I1: Last Checked | J1: Audit Note
A2: Google Skills / GEAR | B2: Develop Agents with ADK | C2: Learning path | D2: Primary | E2: Open resource | F2: https://www.skills.google/paths/3545 | H2: Verified | I2: 46270 | J2: Link verified; sign-in may be required to launch/track course progress.
A3: Google Skills / GEAR | B3: Build Agents with ADK | C3: Course | D3: Primary | E3: Open resource | F3: https://www.skills.google/course_templates/1585 | H3: Verified | I3: 46270 | J3: Link verified; sign-in may be required to launch/track course progress.
A4: Google Skills / GEAR | B4: Build Your First Agent with ADK | C4: Hands-on course | D4: Primary | E4: Open resource | F4: https://partner.skills.google/course_templates/1563 | H4: Verified | I4: 46270 | J4: Link verified; sign-in may be required to launch/track course progress.
A5: Google Skills / GEAR | B5: Architect Multi-Agent Systems with ADK | C5: Learning path | D5: Primary | E5: Open resource | F5: https://www.skills.google/paths/3877 | H5: Verified | I5: 46270 | J5: Link verified; sign-in may be required to launch/track course progress.
A6: Google Skills / GEAR | B6: Build Collaborative Multi-Agent Systems with ADK & MCP | C6: Course | D6: Primary | E6: Open resource | F6: https://www.skills.google/course_templates/1833 | H6: Verified | I6: 46270 | J6: Direct Google Skills course URL verified via current search results; a path-scoped alias also exists.
A7: Google Skills / GEAR | B7: Deploy Production Ready Agents | C7: Learning path | D7: Primary | E7: Open resource | F7: https://www.skills.google/paths/3802 | H7: Verified | I7: 46270 | J7: Link verified; sign-in may be required to launch/track course progress.
A8: Google Skills / GEAR | B8: Use Agent Skills with Multi-Agent Systems | C8: Skill badge | D8: Primary | E8: Open resource | F8: https://www.skills.google/paths/4459/course_templates/1842 | H8: Verified | I8: 46270 | J8: Link verified; sign-in may be required to launch/track course progress.
A9: Google Codelabs | B9: Building AI Agents with ADK: Foundation | C9: Codelab | D9: Primary | E9: Open resource | F9: https://codelabs.developers.google.com/devsite/codelabs/build-agents-with-adk-foundation | H9: Verified | I9: 46270 | J9: Opened successfully during audit.
A10: Google Codelabs | B10: Building AI Agents with ADK: Empowering with Tools | C10: Codelab | D10: Primary | E10: Open resource | F10: https://codelabs.developers.google.com/devsite/codelabs/build-agents-with-adk-empowering-with-tools | H10: Verified | I10: 46270 | J10: Opened successfully during audit.
A11: Google Codelabs | B11: Getting Started with MCP, ADK and A2A | C11: Codelab | D11: Primary | E11: Open resource | F11: https://codelabs.developers.google.com/codelabs/currency-agent | H11: Verified | I11: 46270 | J11: Opened successfully during audit.
A12: Google Codelabs | B12: Multi-Agent Systems with Agent2Agent | C12: Codelab | D12: Primary | E12: Open resource | F12: https://codelabs.developers.google.com/next26/adk-agent2agent | H12: Verified | I12: 46270 | J12: Opened successfully during audit.
A13: Google Codelabs | B13: Multi-Agent Creative Studio: ADK + A2A + MCP | C13: Codelab | D13: Primary | E13: Open resource | F13: https://codelabs.developers.google.com/ai-creative-studio-adk-a2a?hl=en | H13: Verified | I13: 46270 | J13: Opened successfully during audit.
... A63: Harvard / edX | B63: CS50's Introduction to Artificial Intelligence with Python | C63: Course / 7 weeks | D63: Foundations secondary | E63: Open resource | F63: https://cs50.harvard.edu/ai/ | H63: Verified | I63: 46270 | J63: Opened successfully during audit.

Sheet 20-Week Plan
A1: Week | B1: Theme | C1: Primary Inputs | D1: Hands-On Deliverable | E1: Target Hours | F1: Start Date | G1: End Date
A2: 1 | B2: ADK orientation + first agent | C2: GEAR Build Agents; First Agent; Foundation codelab; Google ADK intro video | D2: First ADK Agent | E2: 6 | F2: 46296 | G2: 46302
A3: 2 | B3: ADK foundations | C3: Maurizio 1–7 | D3: Rebuild core agent from memory; architecture note | E3: 6 | F3: 46303 | G3: 46309
A4: 3 | B4: Tool engineering | C4: Maurizio 8–14; Google tools codelab; Anthropic tool article | D4: Tool Contract Lab | E4: 8 | F4: 46310 | G4: 46316
A5: 4 | B5: MCP basics | C5: LinkedIn MCP; Maurizio 27–28; Currency codelab start | D5: MCP Server | E5: 8 | F5: 46317 | G5: 46323
A6: 5 | B6: MCP efficiency + context | C6: Currency codelab finish; Anthropic code execution; Anthropic context article | D6: MCP benchmark | E6: 7 | F6: 46324 | G6: 46330
A7: 6 | B7: Multi-agent + A2A | C7: Maurizio 15–21.5; GEAR multi-agent; A2A codelab | D7: A2A Interop Lab | E7: 9 | F7: 46331 | G7: 46337
A8: 7 | B8: Distributed multi-agent | C8: Creative Studio codelab; Anthropic multi-agent article/video | D8: Multi-Agent Pattern Pack | E8: 9 | F8: 46338 | G8: 46344
A9: 8 | B9: Memory + artifacts | C9: Maurizio 22–23 | D9: Memory & Context Lab | E9: 6 | F9: 46345 | G9: 46351
A10: 9 | B10: Evaluation | C10: Maurizio 24; LinkedIn evals; Anthropic evals | D10: 100-Task Eval Harness v1 | E10: 9 | F10: 46352 | G10: 46358
A11: 10 | B11: Observability + recovery | C11: Maurizio 25–26; LinkedIn failure recovery; Kaggle 2025 Agents Intensive (quality/production units) | D11: Agent Observability | E11: 8 | F11: 46359 | G11: 46365
A12: 11 | B12: Security + governance | C12: LinkedIn governance; Google governance codelab; Anthropic containment | D12: Agent Red Team | E12: 9 | F12: 46366 | G12: 46372
A13: 12 | B13: Production deployment | C13: GEAR Deploy Production Ready; Maurizio 31–32 | D13: Cloud Run deployment | E13: 8 | F13: 46373 | G13: 46379
... A21: 20 | B21: Flagship capstone + writing | C21: Self-directed | D21: Deploy flagship system + publish architecture article | E21: 16 | F21: 46429 | G21: 46435

Sheet CS + Interview Track
A1: Area | B1: Resource | C1: Provider | D1: Priority | E1: Recommended Scope | F1: Why It Matters | G1: Proof / Practice | H1: Cadence | I1: URL | J1: Status | L1: Back to Master Plan
A2: Coding interviews | B2: LeetCode 75 | C2: LeetCode | D2: VERY HIGH | E2: Complete if rusty; otherwise use as diagnostic and focus on weak patterns. | F2: Google-style engineering interviews still require fast, correct algorithmic reasoning. | G2: Solve without hints; after each problem record pattern, complexity, edge cases, and one alternate solution. | H2: 3–5 problems/week in parallel | I2: Open resource | J2: Not Started
A3: Coding interviews | B3: Top Interview 150 | C3: LeetCode | D3: HIGH | E3: Use after LeetCode 75 or selectively for weak topics; do not blindly grind all 150 if already strong. | F3: Broader interview coverage and sustained timed practice. | G3: Weekly 45-minute mock block: 2 problems, explain before coding, test manually, then optimize. | H3: Selective / 2–4 problems/week | I3: Open resource | J3: Not Started
A4: System design | B4: Grokking Modern System Design Interview | C4: Educative | D4: VERY HIGH | E4: Prioritize distributed-system fundamentals + 8–10 case studies + mock interviews. | F4: Senior Google/Anthropic roles require architecture tradeoffs, reliability, consistency, capacity, queues, caches and failure handling. | G4: Do one 45-minute design from a blank page weekly; record requirements, estimates, API/data model, failure modes and tradeoffs. | H4: 2–3 h/week | I4: Open resource | J4: Not Started
A5: ML/AI system design | B5: Grokking the Machine Learning System Design Interview | C5: Educative | D5: VERY HIGH | E5: Complete the framework plus LLM/semantic-search/evaluation-related cases; selectively skim familiar ML basics. | F5: Bridges model quality, data, serving, experimentation and production architecture—the exact interface AI architects need. | G5: Design an LLM/agent platform under explicit latency, cost, eval, safety and rollout constraints. | H5: 1 design every 1–2 weeks | I5: Open resource | J5: Not Started
A6: Agent architecture | B6: Agentic System Design | C6: Educative | D6: HIGH | E6: Use as interview-oriented reinforcement, not as the primary agent course. | F6: Useful for practicing how to explain agent components, orchestration, guardrails and human oversight under interview constraints. | G6: Turn 5 scenarios into architecture decision records: agent vs workflow, single vs multi-agent, tool boundary, memory, eval and fallback. | H6: Selective / ~6 h total | I6: Open resource | J6: Not Started
A7: AI interview drills | B7: AI System Design Interview Questions | C7: Educative | D7: HIGH | E7: Use after system/ML design foundations; emphasize LLM serving, semantic search, safe fallbacks and observability. | F7: Converts broad architecture knowledge into interview-speed reasoning. | G7: Run timed mocks; after each, write what you missed and a better second-pass design. | H7: 1 mock/week late in plan | I7: Open resource | J7: Not Started
A8: Algorithms foundations | B8: MIT 6.006 — Introduction to Algorithms | C8: MIT OpenCourseWare | D8: HIGH | E8: Selective refresh: hashing, graphs, shortest paths, dynamic programming, complexity; do problem sets for weak areas. | F8: Deepens the reasoning behind interview patterns rather than memorizing LeetCode templates. | G8: Complete 2–3 MIT problem sets from your weakest topics without solutions, then compare. | H8: Parallel refresh | I8: Open resource | J8: Not Started
A9: Distributed systems | B9: MIT 6.824 — Distributed Computer Systems Engineering | C9: MIT OpenCourseWare | D9: VERY HIGH | E9: Selective deep study: fault tolerance, replication, consistency, distributed storage, naming and failure recovery. | F9: Agent platforms are distributed systems with stochastic components; these concepts remain foundational even though this OCW edition is older. | G9: Write design notes applying replication/consistency/failure concepts to an agent runtime, tool service and memory service. | H9: 1 topic/week | I9: Open resource | J9: Not Started
A10: Performance systems | B10: MIT 6.172 — Performance Engineering of Software Systems | C10: MIT OpenCourseWare | D10: HIGH | E10: Selective: profiling, caches, parallelism, synchronization, measurement; prioritize if targeting AI systems/infra roles. | F10: Frontier AI engineering increasingly rewards engineers who can reason about latency, throughput, parallelism and compute efficiency. | G10: Profile one agent service end-to-end and make a measured performance improvement with before/after evidence. | H10: Optional depth | I10: Open resource | J10: Not Started
A11: Classical AI | B11: MIT 6.034 — Artificial Intelligence | C11: MIT OpenCourseWare | D11: MEDIUM | E11: Select search, planning, constraints and probabilistic reasoning; skip material duplicated by stronger modern sources. | F11: Gives historical/algorithmic grounding for planning and search techniques that reappear in modern agents. | G11: Implement A*/minimax or a constraint solver and explicitly compare its deterministic search with LLM planning. | H11: Selective | I11: Open resource | J11: Not Started
A12: AI foundations | B12: CS50's Introduction to Artificial Intelligence with Python | C12: Harvard / edX | D12: HIGH | E12: Selective completion recommended for an experienced engineer: search, uncertainty, optimization, learning and language projects. | F12: Hands-on classical AI and ML fundamentals with real Python projects; good gap detector before deeper research material. | G12: Complete at least 3 projects from topics where your intuition is weakest; explain algorithmic choices and failure cases. | H12: Selective / project-driven | I12: Open resource | J12: Not Started

Sheet Stanford Research Track
A1: Order | B1: Resource / Paper | C1: Source | D1: Priority | E1: Why It Matters | F1: Hands-on Activity | G1: Evidence | H1: URL | I1: Status | K1: Back to Master Plan
A2: 1 | B2: CS329A — Self-Improving AI Agents | C2: Stanford | D2: VERY HIGH | E2: The strongest research-oriented course in this plan: test-time scaling, robust verification, tool/code feedback, multi-step planning, RL scaling, self-improvement, memory, coding agents and long-horizon evals. | F2: Follow lectures + core readings; choose one topic for a controlled replication/ablation. | G2: Course notes + replication report | H2: Open | I2: Not Started
A3: 2 | B3: CS329A Past Projects | C3: Stanford | D3: VERY HIGH | E3: Provides concrete examples of the research bar: AppBench, PRIME, meta-agents, ARCHON extensions, reasoning/RL and multi-agent verification. | F3: Review 5 projects; score each on novelty, experimental design, baselines, eval rigor and presentation. Use the best as a capstone-quality benchmark. | G3: Project-review rubric + capstone standard | H3: Open | I3: Not Started
A4: 3 | B4: Scaling Intelligence Lab — Research Themes | C4: Stanford | D4: VERY HIGH | E4: The lab explicitly focuses on scalable/self-improving AI, agentic optimization, automated verifiers/benchmarks, and AI systems. | F4: Use as an ongoing research radar; maintain a one-page map of themes and how your projects connect. | G4: Research map | H4: Open | I4: Not Started
A5: 4 | B5: Scaling Intelligence Lab — Publications | C5: Stanford | D5: VERY HIGH | E5: A concentrated feed of recent work directly relevant to frontier agent engineering. | F5: Read one paper/week during the advanced phase; reproduce or ablate at least one. | G5: Paper notes + one replication | H5: Open | I5: Not Started
A6: 5 | B6: LLM-as-a-Verifier: A General-Purpose Verification Framework | C6: Scaling Intelligence, 2026 | D6: VERY HIGH | E6: Verification is a core bottleneck for self-improving and long-horizon agents. | F6: Build a small verifier benchmark: correctness, false accept/reject, calibration and cost across two models. | G6: Verifier benchmark report | H6: Open paper | I6: Not Started
A7: 6 | B7: Decentralized Multi-Agent Systems with Shared Context | C7: Scaling Intelligence, 2026 | D7: VERY HIGH | E7: Directly relevant to multi-agent coordination and shared-context design beyond hierarchical supervisors. | F7: Compare centralized coordinator vs decentralized/shared-context architecture on the same task set. | G7: Architecture + benchmark | H7: Open paper | I7: Not Started
A8: 7 | B8: TRACE: Capability-Targeted Agentic Training | C8: Scaling Intelligence, 2026 | D8: HIGH | E8: Pushes beyond prompting/frameworks into training agents for targeted capabilities. | F8: Write an experiment design for one capability (tool use, recovery, planning); if compute permits, run a small-scale version. | G8: Experiment proposal/results | H8: Open paper | I8: Not Started
A9: 8 | B9: Weaver: Shrinking the Generation–Verification Gap with Weak Verifiers | C9: Scaling Intelligence, 2025 | D9: VERY HIGH | E9: Shows why verifier quality can limit self-improvement and how weak-verifier regimes behave. | F9: Reproduce a weak-vs-strong verifier comparison on a compact dataset. | G9: Ablation report | H9: Open paper | I9: Not Started
A10: 9 | B10: SPRINT: Interleaved Planning and Parallelized Execution | C10: Scaling Intelligence, 2025 | D10: VERY HIGH | E10: Closely aligned with scalable agent planning/execution and latency-aware orchestration. | F10: Implement sequential plan-execute vs interleaved/parallel execution; compare success, latency and token cost. | G10: Planning benchmark | H10: Open paper | I10: Not Started
A11: 10 | B11: CodeMonkeys: Scaling Test-Time Compute for Software Engineering | C11: Scaling Intelligence, 2025 | D11: VERY HIGH | E11: Connects coding agents, inference-time compute and software-engineering benchmarks. | F11: Run a small coding benchmark varying sampling/test-time budget; plot pass rate vs cost. | G11: Cost-quality curve + analysis | H11: Open paper | I11: Not Started
A12: 11 | B12: Archon: Architecture Search for Inference-Time Techniques | C12: Scaling Intelligence, 2024 | D12: VERY HIGH | E12: A useful bridge from manually designed agent workflows to automated inference architecture search. | F12: Implement 3 inference architectures (single, critic/ranker, planner+critic) and compare quality/cost. | G12: Architecture-search mini study | H12: Open paper | I12: Not Started
A13: 12 | B13: Aakanksha Chowdhery — Research Site | C13: Aakanksha Chowdhery | D13: HIGH | E13: Useful ongoing feed for self-improving agents, RL, reasoning and systems research; also co-instructor context for CS329A. | F13: Check quarterly, not weekly; pull only papers/talks that create a concrete experiment or design question. | G13: Research watch notes | H13: Open | I13: Not Started

Sheet Data + RAG Track
A1: Order | B1: Topic | C1: Resource | D1: Provider | E1: Priority | F1: When | G1: Why It Matters | H1: Hands-on Proof | I1: Evidence | J1: URL | K1: Status | M1: Back to Master Plan
A2: 1 | B2: Retrieval fundamentals | C2: Vector Search and Embeddings | D2: Google Skills / GEAR | E2: VERY HIGH | F2: Weeks 3–5 | G2: Learn embeddings, semantic search, hybrid retrieval and grounded RAG before adding agent orchestration. | H2: Build a small corpus; compare keyword, vector and hybrid retrieval on a labeled query set. | I2: Retrieval benchmark with Recall@K / MRR + failure notes | J2: Open resource | K2: Not Started
A3: 2 | B3: Agentic RAG | C3: Building Agents with Retrieval-Augmented Generation | D3: Google Codelabs | E3: VERY HIGH | F3: Weeks 4–6 | G3: Connect retrieval and structured tools to an ADK agent so the model decides when and how to retrieve. | H3: Complete the financial-analysis lab, then replace one data source with your own corpus/API. | I3: Agentic-RAG repo + eval set | J3: Open resource | K3: Not Started
A4: 3 | B4: Managed RAG | C4: Vertex AI RAG Engine quickstart | D4: Google Cloud | E4: HIGH | F4: Weeks 5–7 | G4: Understand production corpus ingestion, managed retrieval, metadata and retrieval APIs. | H4: Create a RAG corpus, ingest documents, retrieve contexts, and instrument latency/cost. | I4: RAG Engine notebook + architecture note | J4: Open resource | K4: Not Started
A5: 4 | B5: Retrieval quality | C5: Reranking for Vertex AI RAG Engine | D5: Google Cloud | E5: VERY HIGH | F5: Weeks 5–7 | G5: Retrieval quality often dominates answer quality; reranking is a core production technique. | H5: Compare baseline top-K retrieval vs reranked retrieval on at least 30 labeled queries. | I5: Before/after retrieval metrics + cost/latency | J5: Open resource | K5: Not Started
A6: 5 | B6: RAG evaluation | C6: Build a RAG evaluation harness | D6: Self-directed | E6: VERY HIGH | F6: Weeks 6–9 | G6: A RAG system needs separate retrieval and generation metrics; end-answer quality alone hides failure causes. | H6: Measure Recall@K/MRR/nDCG, context precision, groundedness, answer relevance and citation correctness. | I6: Reusable rag-evals package | J6: Open resource | K6: Not Started
A7: 6 | B7: Graph fundamentals | C7: Getting started with Spanner Graph | D7: Google Codelabs | E7: HIGH | F7: Weeks 7–9 | G7: Learn property graphs, nodes/edges, ISO GQL pattern matching, traversal, and relational/graph interoperability. | H7: Complete the codelab, then model one domain from your capstone as nodes/edges and write 8 GQL queries. | I7: Graph schema + GQL query pack | J7: Open resource | K7: Not Started
A8: 7 | B8: GraphRAG architecture | C8: GraphRAG infrastructure using Agent Platform and Spanner Graph | D8: Google Cloud Architecture Center | E8: VERY HIGH | F8: Weeks 8–11 | G8: GraphRAG combines vector retrieval with graph traversal for relationship-aware, multi-hop context. | H8: Design ingestion + serving architecture; explicitly decide what belongs in vectors, relational columns and graph edges. | I8: Architecture diagram + ADR | J8: Open resource | K8: Not Started
A9: 8 | B9: GraphRAG implementation | C9: Build GraphRAG with Spanner Graph and LangChain | D9: Google Cloud | E9: HIGH | F9: Weeks 9–12 | G9: See a practical knowledge-graph construction and retrieval flow using vector and graph queries together. | H9: Implement a miniature GraphRAG corpus and compare answers against vector-only RAG. | I9: RAG vs GraphRAG benchmark | J9: Open resource | K9: Not Started
A10: 9 | B10: Graph algorithms | C10: Spanner Graph algorithms overview | D10: Google Cloud | E10: MEDIUM | F10: Weeks 12–16 | G10: Centrality, clustering, similarity and path finding matter for entity resolution, recommendation, fraud and graph-assisted retrieval. | H10: Run at least two graph algorithms and show when algorithmic graph signals improve retrieval or ranking. | I10: Graph-algorithm experiment | J10: Open resource | K10: Not Started
A11: 10 | B11: Distributed data systems | C11: Spanner: Google's Globally-Distributed Database | D11: Google Research | E11: VERY HIGH | F11: Weeks 10–16 | G11: Build first-principles intuition for sharding, synchronous replication, external consistency, MVCC and TrueTime. | H11: Write a 2-page systems note mapping Spanner guarantees to agent state, memory, tool transactions and multi-region services. | I11: Systems-design note | J11: Open resource | K11: Not Started
A12: 11 | B12: Consistency concepts | C12: TrueTime and external consistency | D12: Google Cloud | E12: HIGH | F12: Weeks 10–16 | G12: Strong consistency and transaction ordering become important when autonomous agents mutate shared state. | H12: Design a shared-agent-state scenario; identify anomalies under weaker consistency and how external consistency changes the design. | I12: Consistency failure analysis | J12: Open resource | K12: Not Started

Sheet Competency Matrix
A1: Domain | B1: Competency | C1: Target Level | D1: Current Level | E1: Readiness % | F1: Google Relevance | G1: Anthropic Relevance | H1: Evidence Required | I1: Primary Track | J1: Go to Track | K1: Key Master Items | L1: Target Date | M1: Assessment Standard | N1: Status | O1: Gap to Target | P1: Notes | Q1: Level Guide | S1: Back to Master Plan
A2: Software Engineering | B2: Python / production coding | C2: 4 | D2: 0 | E2: =IFERROR(MIN(1,D2/C2),0) -> 0 | F2: VERY HIGH | G2: VERY HIGH | H2: Clean tested repo; async/concurrency; APIs; typing; error handling; CI; code review quality. | I2: Master Plan | J2: =HYPERLINK("#'Master Plan'!A1","Open track") -> Open track | K2: Agent runtime; capstone; coding-agent workflow | L2: 46421 | M2: Can implement unfamiliar systems under time pressure and defend design/test choices. | N2: Not Started | O2: =MAX(0,C2-D2) -> 4 | Q2: 0=None | 1=Awareness | 2=Practitioner | 3=Advanced | 4=Independent mastery
A3: Algorithms | B3: Data structures & algorithms | C3: 4 | D3: 0 | E3: =IFERROR(MIN(1,D3/C3),0) -> 0 | F3: VERY HIGH | G3: HIGH | H3: LeetCode 75 diagnostic + timed mocks + complexity reasoning; 2–3 MIT problem sets. | I3: CS + Interview Track | J3: Go to detail | K3: LeetCode 75; MIT 6.006; Top Interview 150 | L3: 46379 | M3: Consistently solves medium interview problems with correct complexity and edge-case reasoning. | N3: Not Started | O3: =MAX(0,C3-D3) -> 4 | Q3: 0=None | 1=Awareness | 2=Practitioner | 3=Advanced | 4=Independent mastery
A4: Systems | B4: Distributed systems | C4: 4 | D4: 0 | E4: =IFERROR(MIN(1,D4/C4),0) -> 0 | F4: VERY HIGH | G4: VERY HIGH | H4: Design notes on consistency, replication, idempotency, retries, failure recovery; MIT 6.824 topics. | I4: CS + Interview Track | J4: Go to detail | K4: MIT 6.824; production deployment; Spanner/TrueTime | L4: 46407 | M4: Can reason from failure models and consistency requirements, not pattern memorization. | N4: Not Started | O4: =MAX(0,C4-D4) -> 4 | Q4: 0=None | 1=Awareness | 2=Practitioner | 3=Advanced | 4=Independent mastery
A5: Systems | B5: System design | C5: 4 | D5: 0 | E5: =IFERROR(MIN(1,D5/C5),0) -> 0 | F5: VERY HIGH | G5: VERY HIGH | H5: 8–10 timed architecture designs with requirements, estimates, APIs, data model, tradeoffs and failure modes. | I5: CS + Interview Track | J5: Go to detail | K5: Educative system design; capstone architecture | L5: 46421 | M5: Can drive a 45–60 minute senior system-design interview end to end. | N5: Not Started | O5: =MAX(0,C5-D5) -> 4 | Q5: 0=None | 1=Awareness | 2=Practitioner | 3=Advanced | 4=Independent mastery
A6: ML Foundations | B6: Classical ML / AI fundamentals | C6: 3 | D6: 0 | E6: =IFERROR(MIN(1,D6/C6),0) -> 0 | F6: HIGH | G6: HIGH | H6: Selective CS50 AI / MIT AI projects; explain search, optimization, uncertainty, learning and evaluation. | I6: CS + Interview Track | J6: Go to detail | K6: CS50 AI; MIT 6.034 | L6: 46351 | M6: Can connect classical search/learning concepts to modern agent behavior and limitations. | N6: Not Started | O6: =MAX(0,C6-D6) -> 3 | Q6: 0=None | 1=Awareness | 2=Practitioner | 3=Advanced | 4=Independent mastery
A7: LLM Foundations | B7: Transformers / inference / model behavior | C7: 3 | D7: 0 | E7: =IFERROR(MIN(1,D7/C7),0) -> 0 | F7: VERY HIGH | G7: VERY HIGH | H7: Technical notes covering attention, tokens, KV cache, prefill/decode, sampling, context, SFT/RLHF/RLAIF, inference cost. | I7: Master Plan | J7: =HYPERLINK("#'Master Plan'!A1","Open track") -> Open track | K7: Context engineering; research papers; performance work | L7: 46393 | M7: Can explain model behavior and system consequences without relying on framework terminology. | N7: Not Started | O7: =MAX(0,C7-D7) -> 3 | Q7: 0=None | 1=Awareness | 2=Practitioner | 3=Advanced | 4=Independent mastery
A8: Agents | B8: Agent loop & framework-free runtime | C8: 4 | D8: 0 | E8: =IFERROR(MIN(1,D8/C8),0) -> 0 | F8: VERY HIGH | G8: VERY HIGH | H8: 2k–4k LOC minimal runtime with tool execution, state, retries, streaming, tracing and eval hooks. | I8: Roadmap | J8: Go to detail | K8: Build minimal agent runtime from scratch | L8: 46421 | M8: Can implement core agent machinery without ADK/LangGraph/CrewAI. | N8: Not Started | O8: =MAX(0,C8-D8) -> 4 | Q8: 0=None | 1=Awareness | 2=Practitioner | 3=Advanced | 4=Independent mastery
A9: Agents | B9: Tool / function-call engineering | C9: 4 | D9: 0 | E9: =IFERROR(MIN(1,D9/C9),0) -> 0 | F9: VERY HIGH | G9: VERY HIGH | H9: Tool contracts, schema tests, A/B tool-selection evals, failure handling and permission boundaries. | I9: Roadmap | J9: Go to detail | K9: Tools & grounding; Anthropic tool engineering | L9: 46330 | M9: Can design deterministic interfaces that nondeterministic agents use reliably. | N9: Not Started | O9: =MAX(0,C9-D9) -> 4 | Q9: 0=None | 1=Awareness | 2=Practitioner | 3=Advanced | 4=Independent mastery
A10: Protocols | B10: MCP | C10: 4 | D10: 0 | E10: =IFERROR(MIN(1,D10/C10),0) -> 0 | F10: VERY HIGH | G10: VERY HIGH | H10: Production-style MCP server + multiple clients + auth/error handling + context/token benchmark. | I10: Roadmap | J10: Go to detail | K10: MCP fundamentals; MCP efficiency; MCP server deployment | L10: 46344 | M10: Can implement, debug and secure MCP outside a single framework. | N10: Not Started | O10: =MAX(0,C10-D10) -> 4 | Q10: 0=None | 1=Awareness | 2=Practitioner | 3=Advanced | 4=Independent mastery
A11: Protocols | B11: A2A / agent interoperability | C11: 4 | D11: 0 | E11: =IFERROR(MIN(1,D11/C11),0) -> 0 | F11: VERY HIGH | G11: HIGH | H11: Cross-vendor ADK/Claude/pure-Python multi-agent system using A2A; agent cards/tasks/artifacts/streaming. | I11: Roadmap | J11: Go to detail | K11: A2A codelabs; agent protocol lab | L11: 46428 | M11: Can explain and implement agent-to-agent boundaries and interoperability. | N11: Not Started | O11: =MAX(0,C11-D11) -> 4 | Q11: 0=None | 1=Awareness | 2=Practitioner | 3=Advanced | 4=Independent mastery
A12: Agents | B12: Multi-agent orchestration | C12: 4 | D12: 0 | E12: =IFERROR(MIN(1,D12/C12),0) -> 0 | F12: VERY HIGH | G12: VERY HIGH | H12: Implement router, sequential, parallel, supervisor and decentralized/shared-context variants; benchmark tradeoffs. | I12: Roadmap | J12: Go to detail | K12: ADK multi-agent; Anthropic research system; decentralized MAS paper | L12: 46414 | M12: Chooses multi-agent only when measured benefits justify coordination cost. | N12: Not Started | O12: =MAX(0,C12-D12) -> 4 | Q12: 0=None | 1=Awareness | 2=Practitioner | 3=Advanced | 4=Independent mastery
A13: Context | B13: State, memory & context engineering | C13: 4 | D13: 0 | E13: =IFERROR(MIN(1,D13/C13),0) -> 0 | F13: VERY HIGH | G13: VERY HIGH | H13: State model + memory strategy + context budget + retrieval policy + multi-session recovery tests. | I13: Roadmap | J13: Go to detail | K13: State & memory; Anthropic context engineering; long-running harness | L13: 46400 | M13: Can decide what enters context, when, why, for how long and at what cost. | N13: Not Started | O13: =MAX(0,C13-D13) -> 4 | Q13: 0=None | 1=Awareness | 2=Practitioner | 3=Advanced | 4=Independent mastery
A14: Grounding | B14: RAG / retrieval engineering | C14: 4 | D14: 0 | E14: =IFERROR(MIN(1,D14/C14),0) -> 0 | F14: VERY HIGH | G14: VERY HIGH | H14: Keyword/vector/hybrid/reranked benchmark; Recall@K/MRR/nDCG; grounded generation and citation evals. | I14: Data + RAG Track | J14: Go to detail | K14: Vector search; Agentic RAG; reranking; RAG eval harness | L14: 46358 | M14: Diagnoses retrieval vs generation failures quantitatively. | N14: Not Started | O14: =MAX(0,C14-D14) -> 4 | Q14: 0=None | 1=Awareness | 2=Practitioner | 3=Advanced | 4=Independent mastery
A15: Grounding | B15: GraphRAG / graph modeling | C15: 3 | D15: 0 | E15: =IFERROR(MIN(1,D15/C15),0) -> 0 | F15: VERY HIGH | G15: HIGH | H15: Property-graph schema + GQL + vector-vs-GraphRAG multi-hop benchmark. | I15: Data + RAG Track | J15: Go to detail | K15: Spanner Graph; GraphRAG architecture; GraphRAG benchmark | L15: 46379 | M15: Knows when relationship-aware traversal adds value beyond vector retrieval. | N15: Not Started | O15: =MAX(0,C15-D15) -> 3 | Q15: 0=None | 1=Awareness | 2=Practitioner | 3=Advanced | 4=Independent mastery
A16: Data Systems | B16: Distributed data / Spanner concepts | C16: 3 | D16: 0 | E16: =IFERROR(MIN(1,D16/C16),0) -> 0 | F16: VERY HIGH | G16: HIGH | H16: Spanner paper notes; TrueTime/external consistency failure analysis; apply guarantees to shared agent state. | I16: Data + RAG Track | J16: Go to detail | K16: Spanner paper; TrueTime; graph data model | L16: 46407 | M16: Can connect database guarantees to autonomous concurrent workflows. | N16: Not Started | O16: =MAX(0,C16-D16) -> 3 | Q16: 0=None | 1=Awareness | 2=Practitioner | 3=Advanced | 4=Independent mastery
A17: Quality | B17: Agent evaluations | C17: 4 | D17: 0 | E17: =IFERROR(MIN(1,D17/C17),0) -> 0 | F17: VERY HIGH | G17: VERY HIGH | H17: 100-task benchmark; trajectory/tool/argument graders; deterministic + LLM judges; regression suite; cost/latency. | I17: Roadmap | J17: Go to detail | K17: Agent eval methodology; benchmark capstone | L17: 46428 | M17: No quality claim without repeatable tasks, metrics and failure taxonomy. | N17: Not Started | O17: =MAX(0,C17-D17) -> 4 | Q17: 0=None | 1=Awareness | 2=Practitioner | 3=Advanced | 4=Independent mastery
A18: Operations | B18: Observability / AgentOps | C18: 4 | D18: 0 | E18: =IFERROR(MIN(1,D18/C18),0) -> 0 | F18: VERY HIGH | G18: VERY HIGH | H18: Traces/spans; tool-call telemetry; latency/tokens/cost/retries; failure diagnosis from traces. | I18: Roadmap | J18: Go to detail | K18: Observability & callbacks; AgentOps; production capstone | L18: 46435 | M18: Can diagnose why an agent failed from evidence rather than saying 'hallucination'. | N18: Not Started | O18: =MAX(0,C18-D18) -> 4 | Q18: 0=None | 1=Awareness | 2=Practitioner | 3=Advanced | 4=Independent mastery
A19: Safety | B19: Security / governance / containment | C19: 4 | D19: 0 | E19: =IFERROR(MIN(1,D19/C19),0) -> 0 | F19: VERY HIGH | G19: VERY HIGH | H19: Threat model + prompt injection/tool poisoning/exfiltration tests + least privilege + sandbox/HITL controls. | I19: Roadmap | J19: Go to detail | K19: Governance; containment; red-team lab | L19: 46435 | M19: Can reason about blast radius, permissions, untrusted context and safe autonomy. | N19: Not Started | O19: =MAX(0,C19-D19) -> 4 | Q19: 0=None | 1=Awareness | 2=Practitioner | 3=Advanced | 4=Independent mastery
... A26: Communication | B26: Technical communication / architecture judgment | C26: 4 | D26: 0 | E26: =IFERROR(MIN(1,D26/C26),0) -> 0 | F26: VERY HIGH | G26: VERY HIGH | H26: Architecture paper + ADRs + benchmark write-up + concise 5–10 minute technical explanation of tradeoffs. | I26: Roadmap | J26: Go to detail | K26: Technical write-up; system-design mocks; flagship capstone | L26: 46435 | M26: Explains complex systems clearly, states tradeoffs and distinguishes evidence from opinion. | N26: Not Started | O26: =MAX(0,C26-D26) -> 4 | Q26: 0=None | 1=Awareness | 2=Practitioner | 3=Advanced | 4=Independent mastery
A29: Competency Summary | B29: Value | D29: Readiness interpretation
A30: Overall readiness | B30: =AVERAGE(E2:E26) -> 0 | D30: 0–49% | E30: Foundations / evidence still developing
A31: At target | B31: =COUNTIF(O2:O26,0) -> 0 | D31: 50–74% | E31: Working proficiency; needs stronger evidence
A32: Interview ready | B32: =COUNTIF(N2:N26,"Interview Ready") -> 0 | D32: 75–99% | E32: Near target; close remaining gaps
A33: Total competencies | B33: 25 | D33: 100% | E33: Target-level evidence demonstrated

Sheet Revision
A1: Revision, Source of Truth & Future Refresh Guide
A2: Purpose: preserve the reasoning behind this workbook, maintain an auditable source hierarchy, and make a future six-month refresh possible with one prompt instead of repeating the entire discovery process.
A4: 1. Workbook Identity / Design Intent
A5: Field | B5: Value | C5: Maintenance note
A6: Workbook | B6: Agentic AI Mastery Worksheet
A7: Built by | B7: ChatGPT — GPT-5.6 Sol | C7: Generated iteratively from the user's requirements; treat Revision as the maintenance contract.
A8: Initial build window | B8: September 4–5, 2026 (America/Chicago) | C8: Inferred from the conversation and generated artifact sequence; not a cryptographic audit trail.
A9: Formal program start | B9: October 1, 2026 | C9: 20 seven-day study blocks.
A10: Original program end | B10: February 17, 2027 | C10: Preserve this historical baseline even if a future refresh rolls unfinished work forward.
A11: Next formal six-month audit | B11: March 5, 2027 | C11: Use the master refresh prompt below; refresh sooner if a major protocol/framework release materially changes the plan.
A12: Primary goal | B12: Become independently strong enough in agent/AI systems engineering to compete for Google / Anthropic-caliber engineering roles. | C12: Optimize for engineering depth, measurable evidence, systems judgment and research fluency—not badge count.
A13: Learning operating model | B13: ~30% structured learning / ~70% building, breaking, evaluating, deploying and writing. | C13: Every major resource should produce evidence.
A14: User context | B14: Chief AI and Software Architect; CLI-heavy; ChatGPT Plus/Codex; GEAR + Google Developer Program; Udemy, LinkedIn Learning, LeetCode and Educative subscriptions. | C14: Do not assume a Claude subscription is required; use Anthropic API/Claude Code only when it adds distinct learning value.
A16: 2. Version History — Reverse Engineered from This Conversation
A17: Version | B17: Date | C17: What changed | D17: Design decision / why | E17: Artifact lineage | F17: Status
A18: v1 | B18: Sep 4, 2026 | C18: Initial consolidated agentic-AI worksheet: Google Skills/GEAR, Codelabs, Maurizio ADK, Anthropic, LinkedIn Learning, Udemy, YouTube; ~50 roadmap items, 16 labs, 20-week plan. | D18: Courses are inputs; hands-on evidence is the output. | E18: agentic_ai_mastery_worksheet.xlsx | F18: Superseded
A19: v2 | B19: Sep 4, 2026 | C19: Priority labels changed to VERY HIGH / HIGH / MEDIUM; hyperlinks audited; Kaggle + Google intensives added; roadmap expanded. | D19: Prefer plain-language priority tiers; treat Kaggle Google intensives as first-party hands-on reinforcement. | E19: agentic_ai_mastery_worksheet_v2.xlsx | F19: Superseded
A20: v3 | B20: Sep 4, 2026 | C20: Added LeetCode/Educative/MIT/Harvard interview/foundations track and Stanford CS329A / Scaling Intelligence research track. | D20: Separate agent-engineering curriculum from CS/interview foundations and frontier research. | E20: agentic_ai_mastery_worksheet_v3.xlsx | F20: Superseded
A21: v4 | B21: Sep 5, 2026 | C21: Added Master Plan, Data + RAG Track, GraphRAG/Spanner concepts, internal navigation and wider link repair. | D21: Use one canonical ordered plan; RAG/GraphRAG/data systems are production competencies, not optional trivia. | E21: agentic_ai_mastery_worksheet_v4.xlsx | F21: Superseded
A22: v5 | B22: Sep 5, 2026 | C22: Added 25-competency readiness matrix and anchored dates to Oct 1, 2026 → Feb 17, 2027. | D22: Measure readiness through independent evidence, not course completion. | E22: agentic_ai_mastery_worksheet_v5.xlsx | F22: Superseded
A23: v6 | B23: Sep 5, 2026 | C23: Added this Revision/SOT/maintenance sheet and a reusable six-month refresh prompt. | D23: Future updates must preserve history, completed evidence, notes and competency scores while replacing stale content. | E23: agentic_ai_mastery_worksheet_v6.xlsx | F23: Superseded
A24: v7 | B24: Sep 5, 2026 | C24: Re-audited Platform Library links; converted the library to a dedicated native clickable Open Link column, retained canonical/raw URLs, and added validation date/status/notes. | D24: Link usability must be explicit and independently auditable; avoid relying on spreadsheet viewers to auto-link plain URL text. | E24: agentic_ai_mastery_worksheet_v7.xlsx | F24: Current
A25: 3. Source of Truth (SOT) Registry & Precedence
A26: Tier | B26: Source / Portal | C26: Canonical URL | D26: Trust for | E26: Refresh cadence | F26: Precedence / caveat | G26: Last verified | H26: Status
A27: T0 — Protocol | B27: Model Context Protocol specification | C27: https://modelcontextprotocol.io/specification/2026-07-28 | D27: MCP protocol requirements, security, transports, extensions, SDK compatibility | E27: Before MCP labs + every formal refresh | F27: Protocol spec overrides courses, videos and framework wrappers. At workbook creation, current spec = 2026-07-28. | G27: Sep 5, 2026 | H27: Authoritative
A28: T0 — Protocol | B28: Agent2Agent (A2A) latest specification | C28: https://a2a-protocol.org/latest/specification | D28: A2A protocol, agent cards, task lifecycle, bindings, extensions, security | E28: Before A2A labs + every formal refresh | F28: Always resolve /latest; at workbook creation the released standard is 1.0.0. Ignore older tutorial behavior if it conflicts. | G28: Sep 5, 2026 | H28: Authoritative
A29: T1 — Vendor | B29: Google Skills / GEAR | C29: https://www.skills.google/ | D29: Current Google agent learning paths, badges, course structure | E29: Quarterly / formal refresh | F29: Primary curriculum source for Google ecosystem. Verify paths/course IDs; do not assume old URLs remain canonical. | G29: Sep 5, 2026 | H29: Authoritative
A30: T1 — Vendor | B30: Google Codelabs | C30: https://codelabs.developers.google.com/ | D30: Current hands-on Google labs | E30: Quarterly / before assigned lab | F30: Prefer current codelab over screenshots/blog summaries. Recheck prerequisites and product names. | G30: Sep 5, 2026 | H30: Authoritative
A31: T1 — Vendor | B31: Google Agent Development Kit docs | C31: https://adk.dev/ | D31: ADK APIs, supported languages, deployment, tools, evaluation, Agent Skills | E31: Monthly during active ADK work | F31: Documentation/version behavior overrides training repo examples. | G31: Sep 5, 2026 | H31: Authoritative
A32: T1 — Vendor | B32: Google Cloud / Vertex AI documentation | C32: https://docs.cloud.google.com/ | D32: Vertex AI, Agent Engine, RAG Engine, Spanner/Spanner Graph, IAM, deployment | E32: Before production/RAG/data labs | F32: Use docs and Architecture Center for product behavior. Price/feature availability must be freshly checked. | G32: Sep 5, 2026 | H32: Authoritative
A33: T1 — Vendor | B33: Kaggle + Google Learn Guides | C33: https://www.kaggle.com/learn-guide/5-day-agents | D33: Google-authored hands-on notebooks, intensives and capstones | E33: Formal refresh | F33: Use Google-authored intensives as practice; do not let them duplicate completed core work. | G33: Sep 5, 2026 | H33: Primary
A34: T1 — Vendor | B34: Anthropic Engineering | C34: https://www.anthropic.com/engineering | D34: Agent patterns, context, tools, evals, security, long-running harnesses | E34: Monthly / formal refresh | F34: First-party engineering lessons; distinguish product guidance from protocol standards. | G34: Sep 5, 2026 | H34: Authoritative
A35: T1 — Vendor | B35: Claude Code documentation | C35: https://code.claude.com/docs | D35: Claude Code workflows, permissions, agentic coding practices | E35: Before Claude Code comparison labs | F35: Use only if Claude Code is part of a deliberate cross-vendor comparison; subscription not required for the overall plan. | G35: Sep 5, 2026 | H35: Authoritative
A36: T1 — Vendor | B36: OpenAI Developers / Codex | C36: https://developers.openai.com/ | D36: Codex CLI/SDK, coding-agent workflows, OpenAI developer guidance | E36: Monthly during CLI-heavy work | F36: Primary SOT for the user's existing ChatGPT Plus/Codex workflow. Recheck current CLI capabilities and plan boundaries. | G36: Sep 5, 2026 | H36: Authoritative
A37: T1 — Academic | B37: Stanford CS329A | C37: https://cs329a.stanford.edu/ | D37: Self-improving agents, readings, research-project bar | E37: Each offering / formal refresh | F37: Course site + primary papers override summaries. Preserve research replication requirement. | G37: Sep 5, 2026 | H37: Primary
... A46: T3 — Community | B46: Maurizio Ipsale ADK Training | C46: https://github.com/mauripsale/doc-adk-training | D46: Deep, structured hands-on ADK practice | E46: Monthly during ADK phase | F46: High-value community/GDE resource; always reconcile with current ADK docs when examples differ. | G46: Sep 5, 2026 | H46: Supplemental
A48: 4. Change-Control Rules — What a Future Refresh Must Preserve
A49: Rule | B49: Required behavior | C49: Why
A50: Preserve history | B50: Never overwrite prior completion dates, Status, Notes, evidence links, Current Level scores or prior version history. Append a new version entry. | C50: The workbook is both a plan and a learning record.
A51: Roll forward, do not reset | B51: If unfinished work remains after Feb 17, 2027, create a revised remaining-work schedule while retaining the original Oct 1–Feb 17 baseline. | C51: Protects comparability between plan and actual progress.
A52: Official > derived | B52: When official specs/docs conflict with a course, video, blog or repo, update the workbook to the official behavior and mark the older resource as stale/legacy. | C52: Avoids learning deprecated APIs/protocol behavior.
A53: No curriculum inflation | B53: Do not add a resource merely because it exists. It must close a competency gap, replace stale material, or materially outperform an existing resource. | C53: The limiting factor is deliberate practice, not content availability.
A54: Evidence gate | B54: Every VERY HIGH/HIGH learning item must lead to code, evals, a design artifact, benchmark, deployment, red-team output, research note or timed interview evidence. | C54: Completion without evidence does not increase readiness.
A55: 30/70 guardrail | B55: Keep structured consumption near 30% and hands-on engineering near 70%. If the update adds >10 learning hours, identify what is removed or downgraded. | C55: Prevents subscription/catalog accumulation.
A56: Protocol > framework | B56: Keep MCP/A2A and framework-free runtime knowledge independent of ADK/LangGraph/CrewAI/Claude/OpenAI wrappers. | C56: Frameworks change faster than architecture concepts.
A57: Cross-vendor by design | B57: Maintain at least one project that uses two model vendors and one framework-free component, with measured comparison rather than brand preference. | C57: Shows transferable agent engineering judgment.
A58: Measure RAG separately | B58: Retain retrieval metrics (Recall@K/MRR/nDCG), groundedness/citation evaluation and GraphRAG comparison; do not collapse everything into end-answer judging. | C58: Makes retrieval failures diagnosable.
A59: Research means experiments | B59: Keep at least one paper replication/ablation. Reading papers alone should not satisfy the research competency. | C59: Frontier roles reward experimental judgment.
A60: Portfolio concentration | B60: Prefer ~4 excellent repositories plus a small number of research/benchmark artifacts over dozens of tutorial repositories. | C60: Signal quality > artifact count.
A61: Link hygiene | B61: Audit every external URL during a formal refresh; replace redirects/deprecated paths with canonical links and mark inaccessible subscription resources explicitly. | C61: Avoids a plan that decays silently.
A63: 5. Formal Refresh Checklist
A64: # | B64: Check | C64: Pass condition | D64: If failed | E64: Suggested cadence | F64: Owner | G64: Last run | H64: Result
A65: 1 | B65: Read Revision first | C65: Future assistant explicitly preserves history and applies SOT precedence. | D65: Stop and restart from the master prompt. | E65: Every formal refresh | F65: ChatGPT + user | G65: Sep 5, 2026 | H65: Baseline
A66: 2 | B66: Audit MCP and A2A versions | C66: Latest released specs identified; breaking/deprecated concepts mapped to affected labs. | D66: Update protocol labs and notes before anything else. | E66: Monthly / refresh | F66: ChatGPT | G66: Sep 5, 2026 | H66: MCP 2026-07-28; A2A 1.0.0
A67: 3 | B67: Audit ADK / Google agent stack | C67: Current ADK docs, Skills/GEAR paths, Codelabs and Agent Engine concepts verified. | D67: Replace stale APIs/courses and adjust hands-on tasks. | E67: Quarterly / refresh | F67: ChatGPT | G67: Sep 5, 2026 | H67: Baseline
A68: 4 | B68: Audit Anthropic/OpenAI coding-agent changes | C68: Current Claude Code and Codex workflows checked; only meaningful deltas added. | D68: Update comparison labs; avoid adding duplicate tool-specific content. | E68: Quarterly / refresh | F68: ChatGPT | G68: Sep 5, 2026 | H68: Baseline
A69: 5 | B69: Audit current Google/Anthropic role signals | C69: Review a representative sample of current engineering/research job descriptions and official hiring material. | D69: Update competencies only when patterns recur across roles; do not overfit one posting. | E69: Formal refresh | F69: ChatGPT | G69: Sep 5, 2026 | H69: Pending future audit
A70: 6 | B70: Audit URLs | C70: No confirmed broken required links; canonical redirects normalized. | D70: Repair URLs or mark resource deprecated. | E70: Formal refresh | F70: ChatGPT | G70: Sep 5, 2026 | H70: Platform Library: 62/62 destinations validated Sep 5, 2026; no confirmed broken links.
A71: 7 | B71: Audit duplication | C71: Each new resource has a unique reason to exist. | D71: Remove/downgrade overlapping courses. | E71: Formal refresh | F71: ChatGPT + user | G71: Sep 5, 2026 | H71: Baseline
A72: 8 | B72: Re-score competency matrix | C72: Current Level reflects evidence actually produced; target levels remain role-relevant. | D72: Ask for evidence or keep score unchanged. | E72: Monthly / refresh | F72: User + ChatGPT | G72: Sep 5, 2026 | H72: Initialized
A73: 9 | B73: Rebuild remaining-work dates | C73: New schedule respects completed work and realistic weekly capacity. | D73: Create revised dates, do not rewrite history. | E73: As needed | F73: ChatGPT + user | G73: Sep 5, 2026 | H73: Original plan Oct 1–Feb 17
A74: 10 | B74: Publish revision diff | C74: Revision sheet records what was added, removed, replaced, reprioritized and why. | D74: Do not ship the updated workbook without a diff. | E74: Every formal refresh | F74: ChatGPT | G74: Sep 5, 2026 | H74: v6 baseline
A76: 6. COPY-READY MASTER REFRESH PROMPT — use this with the workbook attached
A77: Master prompt (copy the full text from cell B below): | B77: You are updating an existing Excel workbook called “Agentic AI Mastery Worksheet”. Treat the attached workbook as a persistent learning system and historical record, NOT as a blank template. ROLE Act as a principal AI/agent systems curriculum architect, senior software/AI systems interviewer, research mentor, and spreadsheet maintainer. Your job is to refresh the workbook for current reality while preserving the user’s accumulated evidence and history. USER / GOAL CONTEXT - User is a Chief AI and Software Architect. - Goal: reach independent engineering/research depth competitive with Google, Anthropic, and similarly demanding AI/agent systems teams. - User is CLI-heavy and already has ChatGPT Plus/Codex. Do not require an additional Claude subscription to make the roadmap work; Claude Code/API should be included only when it teaches a distinct cross-vendor capability. - User participates in Google GEAR and Google Developer Program. - User has access to Google Skills, Google Codelabs, Kaggle, Udemy, LinkedIn Learning, LeetCode and Educative. - The original study program starts October 1, 2026 and ends February 17, 2027. Preserve that baseline even if you roll unfinished work forward. - Core principle: approximately 30% learning/reading and 70% building, breaking, evaluating, deploying, benchmarking and writing. - Portfolio quality and measurable evidence matter more than badge/course count. FIRST ACTIONS 1. Read the “Revision” worksheet completely. 2. Read “Master Plan”, “Competency Matrix”, “20-Week Plan”, “Roadmap”, “Hands-On Labs”, “Data + RAG Track”, “CS + Interview Track”, “Stanford Research Track”, and “Platform Library”. 3. Preserve all user-entered Status fields, completion evidence, dates, Notes, Current Level scores, custom annotations, and prior Revision/version history. 4. Do NOT silently reset a competency score or completed item because the curriculum changed. FRESH WEB / SOURCE AUDIT — REQUIRED Browse current authoritative sources before making recommendations. Use the Source of Truth hierarchy in the Revision sheet. At minimum, verify: - Latest Model Context Protocol specification and migration/deprecation notes. - Latest Agent2Agent (A2A) released specification and notable breaking changes. - Current Google ADK documentation, supported languages/features, Agent Skills, eval/observability/deployment guidance. - Current Google Skills/GEAR agent learning paths and relevant Google Codelabs. - Current Vertex AI / Agent Engine / RAG Engine / Spanner Graph guidance when those topics remain relevant. - Current Kaggle + Google agent intensive materials if still available. - Current Anthropic Engineering articles, Claude Code best practices, context/tool/eval/security/long-running-agent guidance. - Current OpenAI/Codex CLI/SDK/workflow guidance because the user is CLI-heavy and already uses ChatGPT Plus/Codex. - Current Stanford CS329A and Scaling Intelligence research material. - Current MIT OCW / Harvard CS50 resources only if the underlying course pages changed. - Current LeetCode/Educative/LinkedIn Learning/Udemy offerings only to determine whether they still fill a gap. - A representative sample of CURRENT Google and Anthropic engineering/research job descriptions or official hiring signals. Extract recurring competencies; do not overfit to a single posting. SOURCE PRECEDENCE 1. Protocol specifications / standards + primary research papers. 2. Official vendor product documentation and first-party engineering material. 3. Official first-party training/codelabs. 4. University course sites / primary research labs. 5. LeetCode/Educative/LinkedIn/Udemy curated practice. 6. Official YouTube talks as reinforcement. 7. Community repos/blogs. If a lower-tier source conflicts with a higher-tier source, the higher-tier source wins and the workbook must say why the lower-tier item was changed or deprecated. AUDIT THE EXISTING CURRICULUM For every existing required/high-priority item, determine one of: KEEP — still current and uniquely valuable. UPDATE — same resource, but hands-on proof/URL/version must change. REPLACE — stale or weaker than a newer authoritative resource. DOWNGRADE — useful but redundant. REMOVE/ARCHIVE — obsolete, broken or no longer contributes to a competency. Do not delete historical evidence. Archive/deprecate cleanly and record the reason. ANTI-CURRICULUM-INFLATION RULE Do not add a course simply because you found it. A new resource must: (a) close a competency gap, (b) replace something stale, (c) materially increase technical depth, (d) supply a better hands-on lab, or (e) reflect a durable shift in the field. If you add more than ~10 net learning hours, explicitly remove/downgrade other material or explain the workload tradeoff. TECHNICAL COVERAGE THAT MUST REMAIN Maintain strong evidence-oriented coverage for: - Python/software engineering, algorithms, distributed systems and senior system design. - LLM fundamentals: tokens, attention, KV cache, prefill/decode, sampling, context, instruction tuning/RL, inference economics. - Framework-free agent loop/runtime. - Tool/function-call engineering. - MCP and A2A independent of any one framework. - Single vs multi-agent architecture and measured orchestration tradeoffs. - State, memory, context engineering and long-running-agent continuity. - RAG: chunking, embeddings, hybrid retrieval, reranking, retrieval metrics, groundedness/citations. - Graph/GraphRAG and distributed-data concepts where they add real architectural value. - Agent evals: task sets, trajectory/tool/argument grading, deterministic graders, LLM judges, regression, latency/tokens/cost. - Observability / AgentOps. - Security: prompt injection, tool poisoning, exfiltration, least privilege, sandboxing, HITL, blast-radius containment. - Deployment/reliability/CI/CD. - Coding agents and CLI workflows. - Research paper comprehension and at least one controlled replication/ablation. - Technical communication / architecture judgment. EVIDENCE RULE A VERY HIGH or HIGH item should normally result in at least one of: - runnable code, - tests/evals, - benchmark, - architecture/ADR, - deployment/runbook, - security/red-team report, - research reproduction/ablation, - timed interview artifact, - technical paper/article. Watching/reading alone does not justify “mastery”. PORTFOLIO RULE Prefer approximately four excellent repositories and a few benchmark/research artifacts over many tutorial repos: 1. framework-free agent runtime, 2. protocol/interoperability lab (MCP + A2A + multiple vendors), 3. eval/benchmark repository, 4. production multi-agent flagship. Update these only if a stronger portfolio structure is justified. CROSS-VENDOR RULE The curriculum must not overfit to Google ADK, Anthropic, or OpenAI. Keep at least one project where: - different model vendors are interchangeable, - protocols are implemented directly, - one component is framework-free, - results are compared using quality/cost/latency/reliability metrics. RAG / GRAPH RULE Do not treat “RAG” as one box. Separate retrieval quality from answer generation. Preserve retrieval metrics such as Recall@K, MRR and/or nDCG plus groundedness/citation correctness. Keep GraphRAG only where multi-hop relationships or graph structure demonstrate measured benefit over vector-only retrieval. RESEARCH RULE Research competency requires experiments. Retain or improve at least one paper replication/ablation. A paper-reading list by itself is insufficient. COMPETENCY MATRIX UPDATE For each competency: - preserve user Current Level unless new evidence supplied, - review Target Level against current target-role signals, - update evidence required and target date if necessary, - map the strongest current Master Plan items, - identify the smallest set of actions needed to close the gap. Do not claim “Interview Ready” without evidence. SCHEDULE UPDATE If the original program has already begun or ended: - retain the original Oct 1, 2026–Feb 17, 2027 schedule as history, - generate a “remaining work / next phase” schedule based only on unfinished high-value items and current competency gaps, - do not make past dates look as though they were always planned differently. Use realistic weekly capacity and keep parallel interview work from crowding out building/evals. LINK AUDIT Validate all required external URLs. Normalize canonical redirects. Mark subscription/login-gated resources but do not call them broken merely because they require authentication. Repair stale links. Prefer stable landing pages for sources that frequently change IDs. WORKBOOK OUTPUT Update the existing workbook rather than making a new unrelated structure. At minimum update: - Revision: append a new version row with date, major changes and rationale. - Master Plan: revised canonical sequence and dates. - Competency Matrix: gaps and evidence mappings. - Platform Library: current canonical URLs and deprecated-resource notes. - Relevant domain tracks/labs. - Dashboard KPIs if formulas/ranges changed. Preserve internal navigation and clickable links. FINAL QUALITY GATES Before exporting: - no obvious formula errors, - no duplicate required resources without a stated reason, - no required broken links, - no historical data overwritten, - every VERY HIGH/HIGH item has evidence, - the workload is feasible, - the refresh diff is documented, - sources are cited in the workbook through URLs, - the workbook remains readable and navigable. DELIVERABLE Return one revised .xlsx named with the next version number and provide a concise change summary: 1. what was added, 2. what was removed/replaced, 3. what was reprioritized, 4. which protocol/product changes mattered, 5. which competency gaps should receive the next 8–12 weeks of attention. Do not ask me to rediscover or restate the subscriptions, program goal, original start date, source hierarchy, or operating principles that are already recorded in the Revision sheet. Use the workbook as the source of context.
A79: 7. How to Use This in Six Months
A80: Step | B80: Action | C80: Expected output
A81: 1 | B81: Attach the latest .xlsx to a new ChatGPT conversation. | C81: ChatGPT reads Revision first and treats it as persistent context.
A82: 2 | B82: Copy/paste the full prompt from the Master Prompt cell above. | C82: No need to repeat subscriptions, goals or source lists.
A83: 3 | B83: Add one sentence with the new constraint, e.g. “Refresh this as of March 2027; I completed X/Y/Z and can spend 8 hours/week.” | C83: Refresh is personalized without redoing discovery.
A84: 4 | B84: Ask for a current-source audit and a vNext workbook—not a prose-only roadmap. | C84: Updated artifact + change log.
A85: 5 | B85: Review the Revision diff before accepting changed priorities/dates. | C85: Human judgment remains the final gate.
A86: 6 | B86: Keep the old workbook version rather than overwriting it. | C86: You retain an audit trail of how the curriculum evolved.
A88: 8. Early-Refresh Triggers
A89: Trigger | B89: Why it matters | C89: Action
A90: MCP or A2A major/breaking release | B90: Protocol labs can become technically wrong quickly. | C90: Audit spec + affected labs immediately; do not wait six months.
A91: Google ADK major version / major API restructuring | B91: Training examples, deployment and Agent Skills behavior may change. | C91: Reconcile all ADK-heavy rows against current docs.
A92: Major Codex / Claude Code agent-workflow change | B92: CLI practices, permissions, skills/harness patterns may move quickly. | C92: Update coding-agent comparison only if capability is durable and measurable.
A93: A course/link is deprecated or renamed | B93: Broken learning flow creates avoidable friction. | C93: Replace with canonical source and log the change.
A94: Target role changes | B94: Research engineer, AI systems engineer and product architect require different depth profiles. | C94: Re-score Target Levels before adding courses.
A95: Competency plateau | B95: Many courses completed but Current Level/evidence is not improving. | C95: Stop adding material; assign a harder project/eval/research experiment.
A96: Available weekly hours change materially | B96: An unrealistic schedule is worse than a shorter focused one. | C96: Roll forward unfinished VERY HIGH items and reduce parallel work.
A98: 9. Workbook Navigation
A99: Worksheet | B99: Purpose | C99: Open
A100: Master Plan | B100: Canonical ordered sequence | C100: =HYPERLINK("#'Master Plan'!A1","Open") -> Open
A101: Dashboard | B101: High-level KPIs and operating rules | C101: =HYPERLINK("#'Dashboard'!A1","Open") -> Open
A102: Competency Matrix | B102: Readiness / evidence gaps | C102: =HYPERLINK("#'Competency Matrix'!A1","Open") -> Open
A103: Roadmap | B103: Core agent-engineering resources | C103: =HYPERLINK("#'Roadmap'!A1","Open") -> Open
A104: Hands-On Labs | B104: Build/benchmark/project deliverables | C104: =HYPERLINK("#'Hands-On Labs'!A1","Open") -> Open
A105: Data + RAG Track | B105: RAG, GraphRAG, Spanner/data systems | C105: =HYPERLINK("#'Data + RAG Track'!A1","Open") -> Open
A106: CS + Interview Track | B106: Algorithms/system design/interview prep | C106: =HYPERLINK("#'CS + Interview Track'!A1","Open") -> Open
A107: Stanford Research Track | B107: Frontier research / replication | C107: =HYPERLINK("#'Stanford Research Track'!A1","Open") -> Open
A108: Platform Library | B108: Resource registry and URLs | C108: =HYPERLINK("#'Platform Library'!A1","Open") -> Open
A109: 20-Week Plan | B109: Original Oct 1–Feb 17 timebox | C109: =HYPERLINK("#'20-Week Plan'!A1","Open") -> Open
